{
  "binary": "dataset/98f9fd612166fb5d2d1beff49b7159498e01363fbb80be22a12523e8f41121b4",
  "n_nodes": 66,
  "nodes": {
    "77528": {
      "addr": 77528,
      "size": 80,
      "entropy": 4.845191026294643
    },
    "3146112": {
      "addr": 3146112,
      "size": 0,
      "entropy": -0.0
    },
    "77608": {
      "addr": 77608,
      "size": 8,
      "entropy": 3.0
    },
    "80300": {
      "addr": 80300,
      "size": 20,
      "entropy": 3.446439344671016
    },
    "77616": {
      "addr": 77616,
      "size": 16,
      "entropy": 3.5
    },
    "3145736": {
      "addr": 3145736,
      "size": 0,
      "entropy": -0.0
    },
    "77632": {
      "addr": 77632,
      "size": 48,
      "entropy": 4.438721875540868
    },
    "3146488": {
      "addr": 3146488,
      "size": 0,
      "entropy": -0.0
    },
    "77680": {
      "addr": 77680,
      "size": 72,
      "entropy": 4.751105863686464
    },
    "80320": {
      "addr": 80320,
      "size": 12,
      "entropy": 2.584962500721156
    },
    "3145730": {
      "addr": 3145730,
      "size": 0,
      "entropy": 0.0
    },
    "1048656": {
      "addr": 1048656,
      "size": 0,
      "entropy": -0.0
    },
    "77752": {
      "addr": 77752,
      "size": 4,
      "entropy": 2.0
    },
    "32885": {
      "addr": 32885,
      "size": 2,
      "entropy": 1.0
    },
    "33024": {
      "addr": 33024,
      "size": 24,
      "entropy": 4.584962500721156
    },
    "1048652": {
      "addr": 1048652,
      "size": 0,
      "entropy": -0.0
    },
    "32949": {
      "addr": 32949,
      "size": 12,
      "entropy": 2.9182958340544896
    },
    "33081": {
      "addr": 33081,
      "size": 10,
      "entropy": 3.321928094887362
    },
    "33157": {
      "addr": 33157,
      "size": 12,
      "entropy": 5.221928094887365
    },
    "33181": {
      "addr": 33181,
      "size": 2,
      "entropy": 1.0
    },
    "33202": {
      "addr": 33202,
      "size": 4,
      "entropy": 2.0
    },
    "33218": {
      "addr": 33218,
      "size": 4,
      "entropy": 2.0
    },
    "33252": {
      "addr": 33252,
      "size": 8,
      "entropy": 3.0
    },
    "49872": {
      "addr": 49872,
      "size": 4,
      "entropy": 2.0
    },
    "49877": {
      "addr": 49877,
      "size": 22,
      "entropy": 4.459431618637296
    },
    "49901": {
      "addr": 49901,
      "size": 8,
      "entropy": 3.0
    },
    "49910": {
      "addr": 49910,
      "size": 4,
      "entropy": 2.0
    },
    "49940": {
      "addr": 49940,
      "size": 8,
      "entropy": 3.0
    },
    "49994": {
      "addr": 49994,
      "size": 4,
      "entropy": 2.0
    },
    "50001": {
      "addr": 50001,
      "size": 2,
      "entropy": 1.0
    },
    "50040": {
      "addr": 50040,
      "size": 4,
      "entropy": 2.0
    },
    "50044": {
      "addr": 50044,
      "size": 4,
      "entropy": 2.0
    },
    "50061": {
      "addr": 50061,
      "size": 4,
      "entropy": 1.5
    },
    "50187": {
      "addr": 50187,
      "size": 14,
      "entropy": 3.6644977792004623
    },
    "50255": {
      "addr": 50255,
      "size": 4,
      "entropy": 2.0
    },
    "50475": {
      "addr": 50475,
      "size": 2,
      "entropy": 1.0
    },
    "50259": {
      "addr": 50259,
      "size": 24,
      "entropy": 4.501629167387822
    },
    "66767": {
      "addr": 66767,
      "size": 28,
      "entropy": 4.735926350629035
    },
    "67041": {
      "addr": 67041,
      "size": 4,
      "entropy": 2.0
    },
    "66795": {
      "addr": 66795,
      "size": 8,
      "entropy": 3.0
    },
    "66803": {
      "addr": 66803,
      "size": 16,
      "entropy": 3.875
    },
    "66819": {
      "addr": 66819,
      "size": 6,
      "entropy": 2.584962500721156
    },
    "67045": {
      "addr": 67045,
      "size": 28,
      "entropy": 4.735926350629034
    },
    "66837": {
      "addr": 66837,
      "size": 8,
      "entropy": 3.0
    },
    "66888": {
      "addr": 66888,
      "size": 8,
      "entropy": 3.0
    },
    "66896": {
      "addr": 66896,
      "size": 8,
      "entropy": 3.0
    },
    "66904": {
      "addr": 66904,
      "size": 12,
      "entropy": 3.584962500721156
    },
    "66928": {
      "addr": 66928,
      "size": 4,
      "entropy": 2.0
    },
    "66933": {
      "addr": 66933,
      "size": 12,
      "entropy": 3.584962500721156
    },
    "66945": {
      "addr": 66945,
      "size": 2,
      "entropy": 1.0
    },
    "68541": {
      "addr": 68541,
      "size": 4,
      "entropy": 2.0
    },
    "66977": {
      "addr": 66977,
      "size": 2,
      "entropy": 1.0
    },
    "67021": {
      "addr": 67021,
      "size": 2,
      "entropy": 1.0
    },
    "67013": {
      "addr": 67013,
      "size": 8,
      "entropy": 3.0
    },
    "67100": {
      "addr": 67100,
      "size": 8,
      "entropy": 3.0
    },
    "67119": {
      "addr": 67119,
      "size": 14,
      "entropy": 3.6644977792004623
    },
    "69287": {
      "addr": 69287,
      "size": 4,
      "entropy": 2.0
    },
    "67161": {
      "addr": 67161,
      "size": 8,
      "entropy": 3.0
    },
    "67192": {
      "addr": 67192,
      "size": 4,
      "entropy": 2.0
    },
    "32945": {
      "addr": 32945,
      "size": 4,
      "entropy": 2.771782221599798
    },
    "32771": {
      "addr": 32771,
      "size": 114,
      "entropy": 2.3789484628537987
    },
    "67037": {
      "addr": 67037,
      "size": 4,
      "entropy": 3.0
    },
    "66916": {
      "addr": 66916,
      "size": 12,
      "entropy": 4.0
    },
    "67011": {
      "addr": 67011,
      "size": 2,
      "entropy": 3.321928094887362
    },
    "67113": {
      "addr": 67113,
      "size": 6,
      "entropy": 4.221928094887363
    },
    "67023": {
      "addr": 67023,
      "size": 14,
      "entropy": 4.368522527728206
    }
  }
}