{
  "binary": "dataset/a59095521e29aa1361ebfa76695271650a3480832992c69cb3b4672333dfe587.elf",
  "n_nodes": 212,
  "n_edges": 402,
  "nodes": {
    "32916": {
      "addr": 32916.0,
      "name": "sub_8094",
      "n_blocks": 3.0,
      "total_bytes": 24.0,
      "avg_block_entropy": 2.625,
      "std_block_entropy": 0.8838834764831844,
      "bl_count": 2.0,
      "bl_indirect_count": 0.0,
      "svc_count": 0.0,
      "avg_bytes_per_block": 7.999999997333333,
      "instr_count_est": 6.0
    },
    "32944": {
      "addr": 32944.0,
      "name": "sub_80b0",
      "n_blocks": 6.0,
      "total_bytes": 104.0,
      "avg_block_entropy": 3.4838399849256523,
      "std_block_entropy": 0.24205458960860954,
      "bl_count": 0.0,
      "bl_indirect_count": 0.0,
      "svc_count": 0.0,
      "avg_bytes_per_block": 17.333333330444443,
      "instr_count_est": 26.0
    },
    "33064": {
      "addr": 33064.0,
      "name": "sub_8128",
      "n_blocks": 1.0,
      "total_bytes": 8.0,
      "avg_block_entropy": 2.75,
      "std_block_entropy": 0.0,
      "bl_count": 0.0,
      "bl_indirect_count": 0.0,
      "svc_count": 0.0,
      "avg_bytes_per_block": 7.999999991999999,
      "instr_count_est": 2.0
    },
    "33072": {
      "addr": 33072.0,
      "name": "sub_8130",
      "n_blocks": 5.0,
      "total_bytes": 68.0,
      "avg_block_entropy": 2.8560950497650235,
      "std_block_entropy": 0.6851850059760805,
      "bl_count": 0.0,
      "bl_indirect_count": 0.0,
      "svc_count": 0.0,
      "avg_bytes_per_block": 13.59999999728,
      "instr_count_est": 17.0
    },
    "33160": {
      "addr": 33160.0,
      "name": "sub_8188",
      "n_blocks": 1.0,
      "total_bytes": 8.0,
      "avg_block_entropy": 2.75,
      "std_block_entropy": 0.0,
      "bl_count": 0.0,
      "bl_indirect_count": 0.0,
      "svc_count": 0.0,
      "avg_bytes_per_block": 7.999999991999999,
      "instr_count_est": 2.0
    },
    "33168": {
      "addr": 33168.0,
      "name": "_start",
      "n_blocks": 41.0,
      "total_bytes": 660.0,
      "avg_block_entropy": 3.1035807275918037,
      "std_block_entropy": 0.7329081806975791,
      "bl_count": 11.0,
      "bl_indirect_count": 0.0,
      "svc_count": 0.0,
      "avg_bytes_per_block": 16.097560975217135,
      "instr_count_est": 165.0
    },
    "33212": {
      "addr": 33212.0,
      "name": "sub_81bc",
      "n_blocks": 1.0,
      "total_bytes": 4.0,
      "avg_block_entropy": 2.0,
      "std_block_entropy": 0.0,
      "bl_count": 1.0,
      "bl_indirect_count": 0.0,
      "svc_count": 0.0,
      "avg_bytes_per_block": 3.9999999959999997,
      "instr_count_est": 1.0
    },
    "33228": {
      "addr": 33228.0,
      "name": "sub_81cc",
      "n_blocks": 7.0,
      "total_bytes": 100.0,
      "avg_block_entropy": 3.2509664765139292,
      "std_block_entropy": 0.7576812472255381,
      "bl_count": 0.0,
      "bl_indirect_count": 0.0,
      "svc_count": 0.0,
      "avg_bytes_per_block": 14.28571428367347,
      "instr_count_est": 25.0
    },
    "33328": {
      "addr": 33328.0,
      "name": "sub_8230",
      "n_blocks": 18.0,
      "total_bytes": 232.0,
      "avg_block_entropy": 2.8281982672919006,
      "std_block_entropy": 0.7955654910127153,
      "bl_count": 8.0,
      "bl_indirect_count": 0.0,
      "svc_count": 0.0,
      "avg_bytes_per_block": 12.88888888817284,
      "instr_count_est": 58.0
    },
    "33568": {
      "addr": 33568.0,
      "name": "sub_8320",
      "n_blocks": 34.0,
      "total_bytes": 672.0,
      "avg_block_entropy": 3.449724768929802,
      "std_block_entropy": 0.6289232102111884,
      "bl_count": 6.0,
      "bl_indirect_count": 0.0,
      "svc_count": 0.0,
      "avg_bytes_per_block": 19.76470588177163,
      "instr_count_est": 168.0
    },
    "34164": {
      "addr": 34164.0,
      "name": "sub_8574",
      "n_blocks": 8.0,
      "total_bytes": 108.0,
      "avg_block_entropy": 3.154481317986847,
      "std_block_entropy": 0.7544600104871888,
      "bl_count": 0.0,
      "bl_indirect_count": 0.0,
      "svc_count": 0.0,
      "avg_bytes_per_block": 13.4999999983125,
      "instr_count_est": 27.0
    },
    "34272": {
      "addr": 34272.0,
      "name": "sub_85e0",
      "n_blocks": 27.0,
      "total_bytes": 492.0,
      "avg_block_entropy": 3.277753714608544,
      "std_block_entropy": 0.7121081500954479,
      "bl_count": 3.0,
      "bl_indirect_count": 0.0,
      "svc_count": 0.0,
      "avg_bytes_per_block": 18.222222221547327,
      "instr_count_est": 123.0
    },
    "34384": {
      "addr": 34384.0,
      "name": "sub_8650",
      "n_blocks": 29.0,
      "total_bytes": 1080.0,
      "avg_block_entropy": 4.234089983150273,
      "std_block_entropy": 0.1313759486822031,
      "bl_count": 28.0,
      "bl_indirect_count": 0.0,
      "svc_count": 0.0,
      "avg_bytes_per_block": 37.24137930906064,
      "instr_count_est": 270.0
    },
    "35528": {
      "addr": 35528.0,
      "name": "sub_8ac8",
      "n_blocks": 67.0,
      "total_bytes": 2208.0,
      "avg_block_entropy": 3.5685695979786654,
      "std_block_entropy": 0.9709502817336614,
      "bl_count": 39.0,
      "bl_indirect_count": 0.0,
      "svc_count": 0.0,
      "avg_bytes_per_block": 32.955223880105144,
      "instr_count_est": 552.0
    },
    "37672": {
      "addr": 37672.0,
      "name": "sub_9328",
      "n_blocks": 38.0,
      "total_bytes": 840.0,
      "avg_block_entropy": 3.3787363028204926,
      "std_block_entropy": 0.939020869554873,
      "bl_count": 20.0,
      "bl_indirect_count": 0.0,
      "svc_count": 0.0,
      "avg_bytes_per_block": 22.105263157313022,
      "instr_count_est": 210.0
    },
    "38412": {
      "addr": 38412.0,
      "name": "sub_960c",
      "n_blocks": 38.0,
      "total_bytes": 808.0,
      "avg_block_entropy": 3.391572351074056,
      "std_block_entropy": 0.9433921245786723,
      "bl_count": 20.0,
      "bl_indirect_count": 0.0,
      "svc_count": 0.0,
      "avg_bytes_per_block": 21.263157894177287,
      "instr_count_est": 202.0
    },
    "39136": {
      "addr": 39136.0,
      "name": "sub_98e0",
      "n_blocks": 38.0,
      "total_bytes": 840.0,
      "avg_block_entropy": 3.3784656752903266,
      "std_block_entropy": 0.942456996526957,
      "bl_count": 20.0,
      "bl_indirect_count": 0.0,
      "svc_count": 0.0,
      "avg_bytes_per_block": 22.105263157313022,
      "instr_count_est": 210.0
    },
    "39876": {
      "addr": 39876.0,
      "name": "sub_9bc4",
      "n_blocks": 60.0,
      "total_bytes": 1912.0,
      "avg_block_entropy": 3.561551660430029,
      "std_block_entropy": 0.880731255589294,
      "bl_count": 34.0,
      "bl_indirect_count": 0.0,
      "svc_count": 0.0,
      "avg_bytes_per_block": 31.866666666135558,
      "instr_count_est": 478.0
    },
    "41744": {
      "addr": 41744.0,
      "name": "sub_a310",
      "n_blocks": 64.0,
      "total_bytes": 1972.0,
      "avg_block_entropy": 3.569820216534926,
      "std_block_entropy": 0.9141072723175885,
      "bl_count": 36.0,
      "bl_indirect_count": 0.0,
      "svc_count": 0.0,
      "avg_bytes_per_block": 30.812499999518554,
      "instr_count_est": 493.0
    },
    "43652": {
      "addr": 43652.0,
      "name": "sub_aa84",
      "n_blocks": 62.0,
      "total_bytes": 2072.0,
      "avg_block_entropy": 3.5867588363444995,
      "std_block_entropy": 0.9982708491329727,
      "bl_count": 31.0,
      "bl_indirect_count": 0.0,
      "svc_count": 0.0,
      "avg_bytes_per_block": 33.419354838170655,
      "instr_count_est": 518.0
    },
    "45588": {
      "addr": 45588.0,
      "name": "sub_b214",
      "n_blocks": 60.0,
      "total_bytes": 1912.0,
      "avg_block_entropy": 3.562958799528151,
      "std_block_entropy": 0.8815783492056962,
      "bl_count": 34.0,
      "bl_indirect_count": 0.0,
      "svc_count": 0.0,
      "avg_bytes_per_block": 31.866666666135558,
      "instr_count_est": 478.0
    },
    "47456": {
      "addr": 47456.0,
      "name": "sub_b960",
      "n_blocks": 71.0,
      "total_bytes": 2100.0,
      "avg_block_entropy": 3.4473140191712988,
      "std_block_entropy": 0.9731824833575785,
      "bl_count": 40.0,
      "bl_indirect_count": 0.0,
      "svc_count": 0.0,
      "avg_bytes_per_block": 29.577464788315808,
      "instr_count_est": 525.0
    },
    "49496": {
      "addr": 49496.0,
      "name": "sub_c158",
      "n_blocks": 100.0,
      "total_bytes": 1788.0,
      "avg_block_entropy": 3.2308975542804657,
      "std_block_entropy": 0.8687643483546431,
      "bl_count": 45.0,
      "bl_indirect_count": 0.0,
      "svc_count": 0.0,
      "avg_bytes_per_block": 17.879999999821198,
      "instr_count_est": 447.0
    },
    "51132": {
      "addr": 51132.0,
      "name": "sub_c7bc",
      "n_blocks": 39.0,
      "total_bytes": 1028.0,
      "avg_block_entropy": 3.5607752308752585,
      "std_block_entropy": 0.7222704751951956,
      "bl_count": 21.0,
      "bl_indirect_count": 0.0,
      "svc_count": 0.0,
      "avg_bytes_per_block": 26.35897435829849,
      "instr_count_est": 257.0
    },
    "51968": {
      "addr": 51968.0,
      "name": "sub_cb00",
      "n_blocks": 81.0,
      "total_bytes": 2368.0,
      "avg_block_entropy": 3.4978557620307336,
      "std_block_entropy": 0.944070049973967,
      "bl_count": 42.0,
      "bl_indirect_count": 0.0,
      "svc_count": 0.0,
      "avg_bytes_per_block": 29.234567900873646,
      "instr_count_est": 592.0
    },
    "54268": {
      "addr": 54268.0,
      "name": "sub_d3fc",
      "n_blocks": 74.0,
      "total_bytes": 4060.0,
      "avg_block_entropy": 4.232336198150642,
      "std_block_entropy": 0.8245279010228062,
      "bl_count": 48.0,
      "bl_indirect_count": 0.0,
      "svc_count": 0.0,
      "avg_bytes_per_block": 54.86486486412345,
      "instr_count_est": 1015.0
    },
    "57948": {
      "addr": 57948.0,
      "name": "sub_e25c",
      "n_blocks": 98.0,
      "total_bytes": 1800.0,
      "avg_block_entropy": 3.3134488908629014,
      "std_block_entropy": 0.7840216506854061,
      "bl_count": 70.0,
      "bl_indirect_count": 0.0,
      "svc_count": 0.0,
      "avg_bytes_per_block": 18.36734693858809,
      "instr_count_est": 450.0
    },
    "59800": {
      "addr": 59800.0,
      "name": "sub_e998",
      "n_blocks": 4.0,
      "total_bytes": 124.0,
      "avg_block_entropy": 3.902963686369355,
      "std_block_entropy": 0.6087120690804054,
      "bl_count": 0.0,
      "bl_indirect_count": 0.0,
      "svc_count": 0.0,
      "avg_bytes_per_block": 30.99999999225,
      "instr_count_est": 31.0
    },
    "59892": {
      "addr": 59892.0,
      "name": "sub_e9f4",
      "n_blocks": 6.0,
      "total_bytes": 208.0,
      "avg_block_entropy": 4.107416007460744,
      "std_block_entropy": 0.5104181770754911,
      "bl_count": 0.0,
      "bl_indirect_count": 0.0,
      "svc_count": 0.0,
      "avg_bytes_per_block": 34.666666660888886,
      "instr_count_est": 52.0
    },
    "60068": {
      "addr": 60068.0,
      "name": "sub_eaa4",
      "n_blocks": 1.0,
      "total_bytes": 16.0,
      "avg_block_entropy": 3.577819531114783,
      "std_block_entropy": 0.0,
      "bl_count": 0.0,
      "bl_indirect_count": 0.0,
      "svc_count": 0.0,
      "avg_bytes_per_block": 15.999999983999999,
      "instr_count_est": 4.0
    },
    "60088": {
      "addr": 60088.0,
      "name": "sub_eab8",
      "n_blocks": 1.0,
      "total_bytes": 16.0,
      "avg_block_entropy": 3.577819531114783,
      "std_block_entropy": 0.0,
      "bl_count": 0.0,
      "bl_indirect_count": 0.0,
      "svc_count": 0.0,
      "avg_bytes_per_block": 15.999999983999999,
      "instr_count_est": 4.0
    },
    "60108": {
      "addr": 60108.0,
      "name": "sub_eacc",
      "n_blocks": 345.0,
      "total_bytes": 4256.0,
      "avg_block_entropy": 2.9986998931468887,
      "std_block_entropy": 0.530987922584861,
      "bl_count": 175.0,
      "bl_indirect_count": 0.0,
      "svc_count": 0.0,
      "avg_bytes_per_block": 12.336231884022213,
      "instr_count_est": 1064.0
    },
    "64128": {
      "addr": 64128.0,
      "name": "sub_fa80",
      "n_blocks": 1.0,
      "total_bytes": 16.0,
      "avg_block_entropy": 3.327819531114783,
      "std_block_entropy": 0.0,
      "bl_count": 0.0,
      "bl_indirect_count": 0.0,
      "svc_count": 0.0,
      "avg_bytes_per_block": 15.999999983999999,
      "instr_count_est": 4.0
    },
    "64152": {
      "addr": 64152.0,
      "name": "sub_fa98",
      "n_blocks": 4.0,
      "total_bytes": 76.0,
      "avg_block_entropy": 3.5212193506215486,
      "std_block_entropy": 0.5508437007692383,
      "bl_count": 3.0,
      "bl_indirect_count": 0.0,
      "svc_count": 0.0,
      "avg_bytes_per_block": 18.99999999525,
      "instr_count_est": 19.0
    },
    "64236": {
      "addr": 64236.0,
      "name": "sub_faec",
      "n_blocks": 53.0,
      "total_bytes": 568.0,
      "avg_block_entropy": 3.0240174841222314,
      "std_block_entropy": 0.3695797152532115,
      "bl_count": 41.0,
      "bl_indirect_count": 0.0,
      "svc_count": 0.0,
      "avg_bytes_per_block": 10.716981131873265,
      "instr_count_est": 142.0
    },
    "64808": {
      "addr": 64808.0,
      "name": "sub_fd28",
      "n_blocks": 112.0,
      "total_bytes": 1916.0,
      "avg_block_entropy": 3.1196471600511972,
      "std_block_entropy": 0.9175183215952266,
      "bl_count": 63.0,
      "bl_indirect_count": 0.0,
      "svc_count": 0.0,
      "avg_bytes_per_block": 17.107142856990116,
      "instr_count_est": 479.0
    },
    "66632": {
      "addr": 66632.0,
      "name": "sub_10448",
      "n_blocks": 1.0,
      "total_bytes": 72.0,
      "avg_block_entropy": 4.472803983491925,
      "std_block_entropy": 0.0,
      "bl_count": 0.0,
      "bl_indirect_count": 0.0,
      "svc_count": 0.0,
      "avg_bytes_per_block": 71.999999928,
      "instr_count_est": 18.0
    },
    "66720": {
      "addr": 66720.0,
      "name": "sub_104a0",
      "n_blocks": 5.0,
      "total_bytes": 76.0,
      "avg_block_entropy": 3.2041214469857993,
      "std_block_entropy": 0.3045593448806364,
      "bl_count": 4.0,
      "bl_indirect_count": 0.0,
      "svc_count": 0.0,
      "avg_bytes_per_block": 15.199999996959999,
      "instr_count_est": 19.0
    },
    "66812": {
      "addr": 66812.0,
      "name": "sub_104fc",
      "n_blocks": 9.0,
      "total_bytes": 268.0,
      "avg_block_entropy": 3.9770822929244107,
      "std_block_entropy": 0.5712748903069047,
      "bl_count": 0.0,
      "bl_indirect_count": 0.0,
      "svc_count": 0.0,
      "avg_bytes_per_block": 29.777777774469136,
      "instr_count_est": 67.0
    },
    "67040": {
      "addr": 67040.0,
      "name": "sub_105e0",
      "n_blocks": 1.0,
      "total_bytes": 16.0,
      "avg_block_entropy": 3.577819531114783,
      "std_block_entropy": 0.0,
      "bl_count": 0.0,
      "bl_indirect_count": 0.0,
      "svc_count": 0.0,
      "avg_bytes_per_block": 15.999999983999999,
      "instr_count_est": 4.0
    },
    "67060": {
      "addr": 67060.0,
      "name": "sub_105f4",
      "n_blocks": 1.0,
      "total_bytes": 16.0,
      "avg_block_entropy": 3.577819531114783,
      "std_block_entropy": 0.0,
      "bl_count": 0.0,
      "bl_indirect_count": 0.0,
      "svc_count": 0.0,
      "avg_bytes_per_block": 15.999999983999999,
      "instr_count_est": 4.0
    },
    "67080": {
      "addr": 67080.0,
      "name": "sub_10608",
      "n_blocks": 1.0,
      "total_bytes": 40.0,
      "avg_block_entropy": 4.58418371977919,
      "std_block_entropy": 0.0,
      "bl_count": 0.0,
      "bl_indirect_count": 0.0,
      "svc_count": 0.0,
      "avg_bytes_per_block": 39.99999996,
      "instr_count_est": 10.0
    },
    "67124": {
      "addr": 67124.0,
      "name": "sub_10634",
      "n_blocks": 4.0,
      "total_bytes": 264.0,
      "avg_block_entropy": 3.957024652291837,
      "std_block_entropy": 1.150934211703175,
      "bl_count": 0.0,
      "bl_indirect_count": 0.0,
      "svc_count": 0.0,
      "avg_bytes_per_block": 65.9999999835,
      "instr_count_est": 66.0
    },
    "67308": {
      "addr": 67308.0,
      "name": "sub_106ec",
      "n_blocks": 4.0,
      "total_bytes": 264.0,
      "avg_block_entropy": 3.957024652291837,
      "std_block_entropy": 1.150934211703175,
      "bl_count": 0.0,
      "bl_indirect_count": 0.0,
      "svc_count": 0.0,
      "avg_bytes_per_block": 65.9999999835,
      "instr_count_est": 66.0
    },
    "67492": {
      "addr": 67492.0,
      "name": "sub_107a4",
      "n_blocks": 111.0,
      "total_bytes": 2096.0,
      "avg_block_entropy": 3.757687153843843,
      "std_block_entropy": 0.184679185468613,
      "bl_count": 110.0,
      "bl_indirect_count": 0.0,
      "svc_count": 0.0,
      "avg_bytes_per_block": 18.882882882712767,
      "instr_count_est": 524.0
    },
    "69812": {
      "addr": 69812.0,
      "name": "sub_110b4",
      "n_blocks": 4.0,
      "total_bytes": 56.0,
      "avg_block_entropy": 3.067165768157001,
      "std_block_entropy": 0.6386144965893152,
      "bl_count": 0.0,
      "bl_indirect_count": 0.0,
      "svc_count": 0.0,
      "avg_bytes_per_block": 13.9999999965,
      "instr_count_est": 14.0
    },
    "69852": {
      "addr": 69852.0,
      "name": "sub_110dc",
      "n_blocks": 8.0,
      "total_bytes": 120.0,
      "avg_block_entropy": 3.1613543757737315,
      "std_block_entropy": 0.5741041708765703,
      "bl_count": 0.0,
      "bl_indirect_count": 0.0,
      "svc_count": 0.0,
      "avg_bytes_per_block": 14.999999998125,
      "instr_count_est": 30.0
    },
    "69936": {
      "addr": 69936.0,
      "name": "sub_11130",
      "n_blocks": 4.0,
      "total_bytes": 56.0,
      "avg_block_entropy": 3.1355259040879266,
      "std_block_entropy": 0.80713029507298,
      "bl_count": 0.0,
      "bl_indirect_count": 0.0,
      "svc_count": 0.0,
      "avg_bytes_per_block": 13.9999999965,
      "instr_count_est": 14.0
    },
    "69972": {
      "addr": 69972.0,
      "name": "sub_11154",
      "n_blocks": 4.0,
      "total_bytes": 52.0,
      "avg_block_entropy": 3.0654605470327527,
      "std_block_entropy": 0.7453981710766553,
      "bl_count": 0.0,
      "bl_indirect_count": 0.0,
      "svc_count": 0.0,
      "avg_bytes_per_block": 12.99999999675,
      "instr_count_est": 13.0
    },
    "70308": {
      "addr": 70308.0,
      "name": "sub_112a4",
      "n_blocks": 8.0,
      "total_bytes": 168.0,
      "avg_block_entropy": 3.625340909468974,
      "std_block_entropy": 0.5140538375398361,
      "bl_count": 5.0,
      "bl_indirect_count": 0.0,
      "svc_count": 0.0,
      "avg_bytes_per_block": 20.999999997375,
      "instr_count_est": 42.0
    },
    "70464": {
      "addr": 70464.0,
      "name": "sub_11340",
      "n_blocks": 14.0,
      "total_bytes": 332.0,
      "avg_block_entropy": 3.1113316281090073,
      "std_block_entropy": 0.8042311350730438,
      "bl_count": 1.0,
      "bl_indirect_count": 0.0,
      "svc_count": 0.0,
      "avg_bytes_per_block": 23.71428571259184,
      "instr_count_est": 83.0
    },
    "70712": {
      "addr": 70712.0,
      "name": "sub_11438",
      "n_blocks": 2.0,
      "total_bytes": 24.0,
      "avg_block_entropy": 3.25,
      "std_block_entropy": 0.5,
      "bl_count": 1.0,
      "bl_indirect_count": 0.0,
      "svc_count": 0.0,
      "avg_bytes_per_block": 11.999999994,
      "instr_count_est": 6.0
    },
    "70736": {
      "addr": 70736.0,
      "name": "sub_11450",
      "n_blocks": 16.0,
      "total_bytes": 264.0,
      "avg_block_entropy": 2.946988351671839,
      "std_block_entropy": 0.65068139654736,
      "bl_count": 1.0,
      "bl_indirect_count": 0.0,
      "svc_count": 0.0,
      "avg_bytes_per_block": 16.49999999896875,
      "instr_count_est": 66.0
    },
    "70940": {
      "addr": 70940.0,
      "name": "sub_1151c",
      "n_blocks": 16.0,
      "total_bytes": 312.0,
      "avg_block_entropy": 3.0400194335301842,
      "std_block_entropy": 0.6882804671129311,
      "bl_count": 1.0,
      "bl_indirect_count": 0.0,
      "svc_count": 0.0,
      "avg_bytes_per_block": 19.49999999878125,
      "instr_count_est": 78.0
    },
    "71168": {
      "addr": 71168.0,
      "name": "sub_11600",
      "n_blocks": 1.0,
      "total_bytes": 4.0,
      "avg_block_entropy": 2.0,
      "std_block_entropy": 0.0,
      "bl_count": 0.0,
      "bl_indirect_count": 0.0,
      "svc_count": 0.0,
      "avg_bytes_per_block": 3.9999999959999997,
      "instr_count_est": 1.0
    },
    "71172": {
      "addr": 71172.0,
      "name": "sub_11604",
      "n_blocks": 1.0,
      "total_bytes": 80.0,
      "avg_block_entropy": 4.923822201987809,
      "std_block_entropy": 0.0,
      "bl_count": 0.0,
      "bl_indirect_count": 0.0,
      "svc_count": 0.0,
      "avg_bytes_per_block": 79.99999992,
      "instr_count_est": 20.0
    },
    "71252": {
      "addr": 71252.0,
      "name": "sub_11654",
      "n_blocks": 9.0,
      "total_bytes": 152.0,
      "avg_block_entropy": 3.053486289151505,
      "std_block_entropy": 1.0635972319722526,
      "bl_count": 2.0,
      "bl_indirect_count": 0.0,
      "svc_count": 1.0,
      "avg_bytes_per_block": 16.888888887012346,
      "instr_count_est": 38.0
    },
    "71368": {
      "addr": 71368.0,
      "name": "sub_116c8",
      "n_blocks": 5.0,
      "total_bytes": 100.0,
      "avg_block_entropy": 3.4554758534200807,
      "std_block_entropy": 0.814980444187792,
      "bl_count": 1.0,
      "bl_indirect_count": 0.0,
      "svc_count": 1.0,
      "avg_bytes_per_block": 19.999999996,
      "instr_count_est": 25.0
    },
    "71448": {
      "addr": 71448.0,
      "name": "sub_11718",
      "n_blocks": 5.0,
      "total_bytes": 52.0,
      "avg_block_entropy": 2.982129994085646,
      "std_block_entropy": 0.5577095005356217,
      "bl_count": 1.0,
      "bl_indirect_count": 0.0,
      "svc_count": 1.0,
      "avg_bytes_per_block": 10.39999999792,
      "instr_count_est": 13.0
    },
    "71492": {
      "addr": 71492.0,
      "name": "sub_11744",
      "n_blocks": 5.0,
      "total_bytes": 52.0,
      "avg_block_entropy": 2.982129994085646,
      "std_block_entropy": 0.5577095005356217,
      "bl_count": 1.0,
      "bl_indirect_count": 0.0,
      "svc_count": 1.0,
      "avg_bytes_per_block": 10.39999999792,
      "instr_count_est": 13.0
    },
    "71536": {
      "addr": 71536.0,
      "name": "sub_11770",
      "n_blocks": 5.0,
      "total_bytes": 52.0,
      "avg_block_entropy": 2.982129994085646,
      "std_block_entropy": 0.5577095005356217,
      "bl_count": 1.0,
      "bl_indirect_count": 0.0,
      "svc_count": 1.0,
      "avg_bytes_per_block": 10.39999999792,
      "instr_count_est": 13.0
    },
    "71580": {
      "addr": 71580.0,
      "name": "sub_1179c",
      "n_blocks": 5.0,
      "total_bytes": 52.0,
      "avg_block_entropy": 2.932129994085646,
      "std_block_entropy": 0.5650246776878487,
      "bl_count": 1.0,
      "bl_indirect_count": 0.0,
      "svc_count": 1.0,
      "avg_bytes_per_block": 10.39999999792,
      "instr_count_est": 13.0
    },
    "71624": {
      "addr": 71624.0,
      "name": "sub_117c8",
      "n_blocks": 5.0,
      "total_bytes": 100.0,
      "avg_block_entropy": 3.4554758534200807,
      "std_block_entropy": 0.814980444187792,
      "bl_count": 1.0,
      "bl_indirect_count": 0.0,
      "svc_count": 1.0,
      "avg_bytes_per_block": 19.999999996,
      "instr_count_est": 25.0
    },
    "71704": {
      "addr": 71704.0,
      "name": "sub_11818",
      "n_blocks": 5.0,
      "total_bytes": 52.0,
      "avg_block_entropy": 2.982129994085646,
      "std_block_entropy": 0.5577095005356217,
      "bl_count": 1.0,
      "bl_indirect_count": 0.0,
      "svc_count": 1.0,
      "avg_bytes_per_block": 10.39999999792,
      "instr_count_est": 13.0
    },
    "71748": {
      "addr": 71748.0,
      "name": "sub_11844",
      "n_blocks": 5.0,
      "total_bytes": 112.0,
      "avg_block_entropy": 3.436299293632189,
      "std_block_entropy": 1.0762845679419348,
      "bl_count": 1.0,
      "bl_indirect_count": 0.0,
      "svc_count": 1.0,
      "avg_bytes_per_block": 22.399999995519998,
      "instr_count_est": 28.0
    },
    "71840": {
      "addr": 71840.0,
      "name": "sub_118a0",
      "n_blocks": 1.0,
      "total_bytes": 12.0,
      "avg_block_entropy": 3.251629167387823,
      "std_block_entropy": 0.0,
      "bl_count": 0.0,
      "bl_indirect_count": 0.0,
      "svc_count": 0.0,
      "avg_bytes_per_block": 11.999999987999999,
      "instr_count_est": 3.0
    },
    "71856": {
      "addr": 71856.0,
      "name": "sub_118b0",
      "n_blocks": 5.0,
      "total_bytes": 52.0,
      "avg_block_entropy": 2.8821299940856457,
      "std_block_entropy": 0.7399093767515194,
      "bl_count": 1.0,
      "bl_indirect_count": 0.0,
      "svc_count": 1.0,
      "avg_bytes_per_block": 10.39999999792,
      "instr_count_est": 13.0
    },
    "71900": {
      "addr": 71900.0,
      "name": "sub_118dc",
      "n_blocks": 5.0,
      "total_bytes": 56.0,
      "avg_block_entropy": 2.965789160896544,
      "std_block_entropy": 0.7714811232586171,
      "bl_count": 1.0,
      "bl_indirect_count": 0.0,
      "svc_count": 1.0,
      "avg_bytes_per_block": 11.199999997759999,
      "instr_count_est": 14.0
    },
    "71948": {
      "addr": 71948.0,
      "name": "sub_1190c",
      "n_blocks": 5.0,
      "total_bytes": 52.0,
      "avg_block_entropy": 2.8821299940856457,
      "std_block_entropy": 0.7399093767515194,
      "bl_count": 1.0,
      "bl_indirect_count": 0.0,
      "svc_count": 1.0,
      "avg_bytes_per_block": 10.39999999792,
      "instr_count_est": 13.0
    },
    "71992": {
      "addr": 71992.0,
      "name": "sub_11938",
      "n_blocks": 9.0,
      "total_bytes": 104.0,
      "avg_block_entropy": 2.8055658831276333,
      "std_block_entropy": 0.8547846936839989,
      "bl_count": 2.0,
      "bl_indirect_count": 0.0,
      "svc_count": 1.0,
      "avg_bytes_per_block": 11.555555554271605,
      "instr_count_est": 26.0
    },
    "72076": {
      "addr": 72076.0,
      "name": "sub_1198c",
      "n_blocks": 5.0,
      "total_bytes": 52.0,
      "avg_block_entropy": 2.8821299940856457,
      "std_block_entropy": 0.7399093767515194,
      "bl_count": 1.0,
      "bl_indirect_count": 0.0,
      "svc_count": 1.0,
      "avg_bytes_per_block": 10.39999999792,
      "instr_count_est": 13.0
    },
    "72120": {
      "addr": 72120.0,
      "name": "sub_119b8",
      "n_blocks": 5.0,
      "total_bytes": 52.0,
      "avg_block_entropy": 2.8821299940856457,
      "std_block_entropy": 0.7399093767515194,
      "bl_count": 1.0,
      "bl_indirect_count": 0.0,
      "svc_count": 1.0,
      "avg_bytes_per_block": 10.39999999792,
      "instr_count_est": 13.0
    },
    "72164": {
      "addr": 72164.0,
      "name": "sub_119e4",
      "n_blocks": 11.0,
      "total_bytes": 176.0,
      "avg_block_entropy": 3.224532059448835,
      "std_block_entropy": 0.7431323847979926,
      "bl_count": 4.0,
      "bl_indirect_count": 0.0,
      "svc_count": 0.0,
      "avg_bytes_per_block": 15.999999998545455,
      "instr_count_est": 44.0
    },
    "72344": {
      "addr": 72344.0,
      "name": "sub_11a98",
      "n_blocks": 19.0,
      "total_bytes": 248.0,
      "avg_block_entropy": 2.878571534953095,
      "std_block_entropy": 0.7320175358193292,
      "bl_count": 10.0,
      "bl_indirect_count": 0.0,
      "svc_count": 0.0,
      "avg_bytes_per_block": 13.052631578260387,
      "instr_count_est": 62.0
    },
    "72596": {
      "addr": 72596.0,
      "name": "sub_11b94",
      "n_blocks": 9.0,
      "total_bytes": 244.0,
      "avg_block_entropy": 3.6176189640967027,
      "std_block_entropy": 0.6410451319886674,
      "bl_count": 1.0,
      "bl_indirect_count": 0.0,
      "svc_count": 0.0,
      "avg_bytes_per_block": 27.111111108098765,
      "instr_count_est": 61.0
    },
    "72804": {
      "addr": 72804.0,
      "name": "sub_11c64",
      "n_blocks": 1.0,
      "total_bytes": 8.0,
      "avg_block_entropy": 2.75,
      "std_block_entropy": 0.0,
      "bl_count": 0.0,
      "bl_indirect_count": 0.0,
      "svc_count": 0.0,
      "avg_bytes_per_block": 7.999999991999999,
      "instr_count_est": 2.0
    },
    "72816": {
      "addr": 72816.0,
      "name": "sub_11c70",
      "n_blocks": 2.0,
      "total_bytes": 48.0,
      "avg_block_entropy": 4.132659765557392,
      "std_block_entropy": 0.25765976555739156,
      "bl_count": 1.0,
      "bl_indirect_count": 0.0,
      "svc_count": 0.0,
      "avg_bytes_per_block": 23.999999988,
      "instr_count_est": 12.0
    },
    "72880": {
      "addr": 72880.0,
      "name": "sub_11cb0",
      "n_blocks": 84.0,
      "total_bytes": 1776.0,
      "avg_block_entropy": 3.4193216228534014,
      "std_block_entropy": 0.8317656961649351,
      "bl_count": 0.0,
      "bl_indirect_count": 0.0,
      "svc_count": 0.0,
      "avg_bytes_per_block": 21.14285714260544,
      "instr_count_est": 444.0
    },
    "72887": {
      "addr": 72887.0,
      "name": "sub_11cb7",
      "n_blocks": 1.0,
      "total_bytes": 2.0,
      "avg_block_entropy": 1.0,
      "std_block_entropy": 0.0,
      "bl_count": 0.0,
      "bl_indirect_count": 0.0,
      "svc_count": 0.0,
      "avg_bytes_per_block": 1.9999999979999998,
      "instr_count_est": 1.0
    },
    "72891": {
      "addr": 72891.0,
      "name": "sub_11cbb",
      "n_blocks": 1.0,
      "total_bytes": 2.0,
      "avg_block_entropy": 1.0,
      "std_block_entropy": 0.0,
      "bl_count": 0.0,
      "bl_indirect_count": 0.0,
      "svc_count": 0.0,
      "avg_bytes_per_block": 1.9999999979999998,
      "instr_count_est": 1.0
    },
    "72895": {
      "addr": 72895.0,
      "name": "sub_11cbf",
      "n_blocks": 1.0,
      "total_bytes": 2.0,
      "avg_block_entropy": 1.0,
      "std_block_entropy": 0.0,
      "bl_count": 0.0,
      "bl_indirect_count": 0.0,
      "svc_count": 0.0,
      "avg_bytes_per_block": 1.9999999979999998,
      "instr_count_est": 1.0
    },
    "72896": {
      "addr": 72896.0,
      "name": "sub_11cc0",
      "n_blocks": 1.0,
      "total_bytes": 4.0,
      "avg_block_entropy": 2.0,
      "std_block_entropy": 0.0,
      "bl_count": 0.0,
      "bl_indirect_count": 0.0,
      "svc_count": 0.0,
      "avg_bytes_per_block": 3.9999999959999997,
      "instr_count_est": 1.0
    },
    "72903": {
      "addr": 72903.0,
      "name": "sub_11cc7",
      "n_blocks": 1.0,
      "total_bytes": 2.0,
      "avg_block_entropy": 1.0,
      "std_block_entropy": 0.0,
      "bl_count": 0.0,
      "bl_indirect_count": 0.0,
      "svc_count": 0.0,
      "avg_bytes_per_block": 1.9999999979999998,
      "instr_count_est": 1.0
    },
    "72907": {
      "addr": 72907.0,
      "name": "sub_11ccb",
      "n_blocks": 1.0,
      "total_bytes": 2.0,
      "avg_block_entropy": 1.0,
      "std_block_entropy": 0.0,
      "bl_count": 0.0,
      "bl_indirect_count": 0.0,
      "svc_count": 0.0,
      "avg_bytes_per_block": 1.9999999979999998,
      "instr_count_est": 1.0
    },
    "72911": {
      "addr": 72911.0,
      "name": "sub_11ccf",
      "n_blocks": 1.0,
      "total_bytes": 2.0,
      "avg_block_entropy": 1.0,
      "std_block_entropy": 0.0,
      "bl_count": 0.0,
      "bl_indirect_count": 0.0,
      "svc_count": 0.0,
      "avg_bytes_per_block": 1.9999999979999998,
      "instr_count_est": 1.0
    },
    "72912": {
      "addr": 72912.0,
      "name": "sub_11cd0",
      "n_blocks": 11.0,
      "total_bytes": 152.0,
      "avg_block_entropy": 3.2703121687490904,
      "std_block_entropy": 0.47809358285532993,
      "bl_count": 0.0,
      "bl_indirect_count": 0.0,
      "svc_count": 0.0,
      "avg_bytes_per_block": 13.81818181692562,
      "instr_count_est": 38.0
    },
    "73035": {
      "addr": 73035.0,
      "name": "sub_11d4b",
      "n_blocks": 1.0,
      "total_bytes": 2.0,
      "avg_block_entropy": 1.0,
      "std_block_entropy": 0.0,
      "bl_count": 0.0,
      "bl_indirect_count": 0.0,
      "svc_count": 0.0,
      "avg_bytes_per_block": 1.9999999979999998,
      "instr_count_est": 1.0
    },
    "73037": {
      "addr": 73037.0,
      "name": "sub_11d4d",
      "n_blocks": 1.0,
      "total_bytes": 4.0,
      "avg_block_entropy": 2.0,
      "std_block_entropy": 0.0,
      "bl_count": 0.0,
      "bl_indirect_count": 0.0,
      "svc_count": 0.0,
      "avg_bytes_per_block": 3.9999999959999997,
      "instr_count_est": 2.0
    },
    "73041": {
      "addr": 73041.0,
      "name": "sub_11d51",
      "n_blocks": 1.0,
      "total_bytes": 4.0,
      "avg_block_entropy": 2.0,
      "std_block_entropy": 0.0,
      "bl_count": 0.0,
      "bl_indirect_count": 0.0,
      "svc_count": 0.0,
      "avg_bytes_per_block": 3.9999999959999997,
      "instr_count_est": 2.0
    },
    "73045": {
      "addr": 73045.0,
      "name": "sub_11d55",
      "n_blocks": 1.0,
      "total_bytes": 4.0,
      "avg_block_entropy": 2.0,
      "std_block_entropy": 0.0,
      "bl_count": 0.0,
      "bl_indirect_count": 0.0,
      "svc_count": 0.0,
      "avg_bytes_per_block": 3.9999999959999997,
      "instr_count_est": 2.0
    },
    "73049": {
      "addr": 73049.0,
      "name": "sub_11d59",
      "n_blocks": 1.0,
      "total_bytes": 4.0,
      "avg_block_entropy": 2.0,
      "std_block_entropy": 0.0,
      "bl_count": 0.0,
      "bl_indirect_count": 0.0,
      "svc_count": 0.0,
      "avg_bytes_per_block": 3.9999999959999997,
      "instr_count_est": 2.0
    },
    "73053": {
      "addr": 73053.0,
      "name": "sub_11d5d",
      "n_blocks": 1.0,
      "total_bytes": 4.0,
      "avg_block_entropy": 2.0,
      "std_block_entropy": 0.0,
      "bl_count": 0.0,
      "bl_indirect_count": 0.0,
      "svc_count": 0.0,
      "avg_bytes_per_block": 3.9999999959999997,
      "instr_count_est": 2.0
    },
    "73057": {
      "addr": 73057.0,
      "name": "sub_11d61",
      "n_blocks": 1.0,
      "total_bytes": 4.0,
      "avg_block_entropy": 2.0,
      "std_block_entropy": 0.0,
      "bl_count": 0.0,
      "bl_indirect_count": 0.0,
      "svc_count": 0.0,
      "avg_bytes_per_block": 3.9999999959999997,
      "instr_count_est": 2.0
    },
    "73061": {
      "addr": 73061.0,
      "name": "sub_11d65",
      "n_blocks": 1.0,
      "total_bytes": 4.0,
      "avg_block_entropy": 2.0,
      "std_block_entropy": 0.0,
      "bl_count": 0.0,
      "bl_indirect_count": 0.0,
      "svc_count": 0.0,
      "avg_bytes_per_block": 3.9999999959999997,
      "instr_count_est": 2.0
    },
    "73065": {
      "addr": 73065.0,
      "name": "sub_11d69",
      "n_blocks": 2.0,
      "total_bytes": 8.0,
      "avg_block_entropy": 1.75,
      "std_block_entropy": 0.25,
      "bl_count": 1.0,
      "bl_indirect_count": 0.0,
      "svc_count": 0.0,
      "avg_bytes_per_block": 3.999999998,
      "instr_count_est": 3.0
    },
    "73072": {
      "addr": 73072.0,
      "name": "sub_11d70",
      "n_blocks": 4.0,
      "total_bytes": 124.0,
      "avg_block_entropy": 3.6136821546599105,
      "std_block_entropy": 0.29538504618767725,
      "bl_count": 0.0,
      "bl_indirect_count": 0.0,
      "svc_count": 0.0,
      "avg_bytes_per_block": 30.99999999225,
      "instr_count_est": 31.0
    },
    "73168": {
      "addr": 73168.0,
      "name": "sub_11dd0",
      "n_blocks": 15.0,
      "total_bytes": 200.0,
      "avg_block_entropy": 2.9772664175867676,
      "std_block_entropy": 0.7389627281926381,
      "bl_count": 0.0,
      "bl_indirect_count": 0.0,
      "svc_count": 0.0,
      "avg_bytes_per_block": 13.333333332444445,
      "instr_count_est": 50.0
    },
    "73352": {
      "addr": 73352.0,
      "name": "sub_11e88",
      "n_blocks": 2.0,
      "total_bytes": 36.0,
      "avg_block_entropy": 3.4946769360836,
      "std_block_entropy": 0.2553230639163997,
      "bl_count": 1.0,
      "bl_indirect_count": 0.0,
      "svc_count": 0.0,
      "avg_bytes_per_block": 17.999999991,
      "instr_count_est": 9.0
    },
    "73388": {
      "addr": 73388.0,
      "name": "sub_11eac",
      "n_blocks": 5.0,
      "total_bytes": 52.0,
      "avg_block_entropy": 2.8821299940856457,
      "std_block_entropy": 0.7399093767515194,
      "bl_count": 1.0,
      "bl_indirect_count": 0.0,
      "svc_count": 1.0,
      "avg_bytes_per_block": 10.39999999792,
      "instr_count_est": 13.0
    },
    "73432": {
      "addr": 73432.0,
      "name": "sub_11ed8",
      "n_blocks": 5.0,
      "total_bytes": 52.0,
      "avg_block_entropy": 2.8821299940856457,
      "std_block_entropy": 0.7399093767515194,
      "bl_count": 1.0,
      "bl_indirect_count": 0.0,
      "svc_count": 1.0,
      "avg_bytes_per_block": 10.39999999792,
      "instr_count_est": 13.0
    },
    "73476": {
      "addr": 73476.0,
      "name": "sub_11f04",
      "n_blocks": 5.0,
      "total_bytes": 52.0,
      "avg_block_entropy": 2.8821299940856457,
      "std_block_entropy": 0.7399093767515194,
      "bl_count": 1.0,
      "bl_indirect_count": 0.0,
      "svc_count": 1.0,
      "avg_bytes_per_block": 10.39999999792,
      "instr_count_est": 13.0
    },
    "73520": {
      "addr": 73520.0,
      "name": "sub_11f30",
      "n_blocks": 5.0,
      "total_bytes": 52.0,
      "avg_block_entropy": 2.8821299940856457,
      "std_block_entropy": 0.7399093767515194,
      "bl_count": 1.0,
      "bl_indirect_count": 0.0,
      "svc_count": 1.0,
      "avg_bytes_per_block": 10.39999999792,
      "instr_count_est": 13.0
    },
    "73564": {
      "addr": 73564.0,
      "name": "sub_11f5c",
      "n_blocks": 5.0,
      "total_bytes": 56.0,
      "avg_block_entropy": 2.965789160896544,
      "std_block_entropy": 0.7714811232586171,
      "bl_count": 1.0,
      "bl_indirect_count": 0.0,
      "svc_count": 1.0,
      "avg_bytes_per_block": 11.199999997759999,
      "instr_count_est": 14.0
    },
    "73612": {
      "addr": 73612.0,
      "name": "sub_11f8c",
      "n_blocks": 5.0,
      "total_bytes": 52.0,
      "avg_block_entropy": 2.8821299940856457,
      "std_block_entropy": 0.7399093767515194,
      "bl_count": 1.0,
      "bl_indirect_count": 0.0,
      "svc_count": 1.0,
      "avg_bytes_per_block": 10.39999999792,
      "instr_count_est": 13.0
    },
    "73656": {
      "addr": 73656.0,
      "name": "sub_11fb8",
      "n_blocks": 5.0,
      "total_bytes": 52.0,
      "avg_block_entropy": 2.8821299940856457,
      "std_block_entropy": 0.7399093767515194,
      "bl_count": 1.0,
      "bl_indirect_count": 0.0,
      "svc_count": 1.0,
      "avg_bytes_per_block": 10.39999999792,
      "instr_count_est": 13.0
    },
    "73700": {
      "addr": 73700.0,
      "name": "sub_11fe4",
      "n_blocks": 5.0,
      "total_bytes": 60.0,
      "avg_block_entropy": 3.004581119064011,
      "std_block_entropy": 0.7986590801466317,
      "bl_count": 1.0,
      "bl_indirect_count": 0.0,
      "svc_count": 1.0,
      "avg_bytes_per_block": 11.9999999976,
      "instr_count_est": 15.0
    },
    "73752": {
      "addr": 73752.0,
      "name": "sub_12018",
      "n_blocks": 5.0,
      "total_bytes": 52.0,
      "avg_block_entropy": 2.8821299940856457,
      "std_block_entropy": 0.7399093767515194,
      "bl_count": 1.0,
      "bl_indirect_count": 0.0,
      "svc_count": 1.0,
      "avg_bytes_per_block": 10.39999999792,
      "instr_count_est": 13.0
    },
    "73796": {
      "addr": 73796.0,
      "name": "sub_12044",
      "n_blocks": 5.0,
      "total_bytes": 60.0,
      "avg_block_entropy": 3.004581119064011,
      "std_block_entropy": 0.7986590801466317,
      "bl_count": 1.0,
      "bl_indirect_count": 0.0,
      "svc_count": 1.0,
      "avg_bytes_per_block": 11.9999999976,
      "instr_count_est": 15.0
    },
    "73848": {
      "addr": 73848.0,
      "name": "sub_12078",
      "n_blocks": 5.0,
      "total_bytes": 56.0,
      "avg_block_entropy": 3.0657891608965437,
      "std_block_entropy": 0.584829283949657,
      "bl_count": 1.0,
      "bl_indirect_count": 0.0,
      "svc_count": 1.0,
      "avg_bytes_per_block": 11.199999997759999,
      "instr_count_est": 14.0
    },
    "73896": {
      "addr": 73896.0,
      "name": "sub_120a8",
      "n_blocks": 5.0,
      "total_bytes": 52.0,
      "avg_block_entropy": 2.982129994085646,
      "std_block_entropy": 0.5577095005356217,
      "bl_count": 1.0,
      "bl_indirect_count": 0.0,
      "svc_count": 1.0,
      "avg_bytes_per_block": 10.39999999792,
      "instr_count_est": 13.0
    },
    "73940": {
      "addr": 73940.0,
      "name": "sub_120d4",
      "n_blocks": 5.0,
      "total_bytes": 48.0,
      "avg_block_entropy": 2.759436093777043,
      "std_block_entropy": 0.5228903199577875,
      "bl_count": 1.0,
      "bl_indirect_count": 0.0,
      "svc_count": 0.0,
      "avg_bytes_per_block": 9.59999999808,
      "instr_count_est": 12.0
    },
    "73988": {
      "addr": 73988.0,
      "name": "sub_12104",
      "n_blocks": 2.0,
      "total_bytes": 24.0,
      "avg_block_entropy": 3.25,
      "std_block_entropy": 0.5,
      "bl_count": 1.0,
      "bl_indirect_count": 0.0,
      "svc_count": 0.0,
      "avg_bytes_per_block": 11.999999994,
      "instr_count_est": 6.0
    },
    "74012": {
      "addr": 74012.0,
      "name": "sub_1211c",
      "n_blocks": 13.0,
      "total_bytes": 208.0,
      "avg_block_entropy": 3.2893863941523867,
      "std_block_entropy": 0.7065197432123843,
      "bl_count": 4.0,
      "bl_indirect_count": 0.0,
      "svc_count": 0.0,
      "avg_bytes_per_block": 15.99999999876923,
      "instr_count_est": 52.0
    },
    "74196": {
      "addr": 74196.0,
      "name": "sub_121d4",
      "n_blocks": 1.0,
      "total_bytes": 36.0,
      "avg_block_entropy": 4.215354779870082,
      "std_block_entropy": 0.0,
      "bl_count": 0.0,
      "bl_indirect_count": 0.0,
      "svc_count": 0.0,
      "avg_bytes_per_block": 35.999999964,
      "instr_count_est": 9.0
    },
    "74232": {
      "addr": 74232.0,
      "name": "sub_121f8",
      "n_blocks": 1.0,
      "total_bytes": 36.0,
      "avg_block_entropy": 4.218128820706467,
      "std_block_entropy": 0.0,
      "bl_count": 0.0,
      "bl_indirect_count": 0.0,
      "svc_count": 0.0,
      "avg_bytes_per_block": 35.999999964,
      "instr_count_est": 9.0
    },
    "74268": {
      "addr": 74268.0,
      "name": "sub_1221c",
      "n_blocks": 1.0,
      "total_bytes": 36.0,
      "avg_block_entropy": 4.218128820706467,
      "std_block_entropy": 0.0,
      "bl_count": 0.0,
      "bl_indirect_count": 0.0,
      "svc_count": 0.0,
      "avg_bytes_per_block": 35.999999964,
      "instr_count_est": 9.0
    },
    "74304": {
      "addr": 74304.0,
      "name": "sub_12240",
      "n_blocks": 21.0,
      "total_bytes": 328.0,
      "avg_block_entropy": 3.1398438218433298,
      "std_block_entropy": 0.6836941293314837,
      "bl_count": 5.0,
      "bl_indirect_count": 0.0,
      "svc_count": 0.0,
      "avg_bytes_per_block": 15.619047618303854,
      "instr_count_est": 82.0
    },
    "74644": {
      "addr": 74644.0,
      "name": "sub_12394",
      "n_blocks": 8.0,
      "total_bytes": 88.0,
      "avg_block_entropy": 2.8666054380141803,
      "std_block_entropy": 0.6423431535199567,
      "bl_count": 3.0,
      "bl_indirect_count": 0.0,
      "svc_count": 0.0,
      "avg_bytes_per_block": 10.999999998625,
      "instr_count_est": 22.0
    },
    "74732": {
      "addr": 74732.0,
      "name": "sub_123ec",
      "n_blocks": 13.0,
      "total_bytes": 224.0,
      "avg_block_entropy": 3.247159075217554,
      "std_block_entropy": 0.48371847438037163,
      "bl_count": 3.0,
      "bl_indirect_count": 0.0,
      "svc_count": 0.0,
      "avg_bytes_per_block": 17.230769229443787,
      "instr_count_est": 56.0
    },
    "74972": {
      "addr": 74972.0,
      "name": "sub_124dc",
      "n_blocks": 21.0,
      "total_bytes": 272.0,
      "avg_block_entropy": 3.082258171828024,
      "std_block_entropy": 0.7234500372929455,
      "bl_count": 6.0,
      "bl_indirect_count": 0.0,
      "svc_count": 0.0,
      "avg_bytes_per_block": 12.952380951764173,
      "instr_count_est": 68.0
    },
    "75252": {
      "addr": 75252.0,
      "name": "sub_125f4",
      "n_blocks": 8.0,
      "total_bytes": 172.0,
      "avg_block_entropy": 3.299460981490851,
      "std_block_entropy": 0.8115233159549065,
      "bl_count": 0.0,
      "bl_indirect_count": 0.0,
      "svc_count": 0.0,
      "avg_bytes_per_block": 21.4999999973125,
      "instr_count_est": 43.0
    },
    "75400": {
      "addr": 75400.0,
      "name": "sub_12688",
      "n_blocks": 9.0,
      "total_bytes": 148.0,
      "avg_block_entropy": 3.1343592369965627,
      "std_block_entropy": 0.736261058762936,
      "bl_count": 0.0,
      "bl_indirect_count": 0.0,
      "svc_count": 0.0,
      "avg_bytes_per_block": 16.444444442617282,
      "instr_count_est": 37.0
    },
    "75540": {
      "addr": 75540.0,
      "name": "sub_12714",
      "n_blocks": 1.0,
      "total_bytes": 32.0,
      "avg_block_entropy": 4.1136085007312415,
      "std_block_entropy": 0.0,
      "bl_count": 0.0,
      "bl_indirect_count": 0.0,
      "svc_count": 0.0,
      "avg_bytes_per_block": 31.999999967999997,
      "instr_count_est": 8.0
    },
    "75572": {
      "addr": 75572.0,
      "name": "sub_12734",
      "n_blocks": 1.0,
      "total_bytes": 20.0,
      "avg_block_entropy": 3.984183719779189,
      "std_block_entropy": 0.0,
      "bl_count": 0.0,
      "bl_indirect_count": 0.0,
      "svc_count": 0.0,
      "avg_bytes_per_block": 19.99999998,
      "instr_count_est": 5.0
    },
    "75592": {
      "addr": 75592.0,
      "name": "sub_12748",
      "n_blocks": 19.0,
      "total_bytes": 256.0,
      "avg_block_entropy": 3.1003233075124026,
      "std_block_entropy": 0.7819970126956586,
      "bl_count": 4.0,
      "bl_indirect_count": 0.0,
      "svc_count": 0.0,
      "avg_bytes_per_block": 13.473684209817174,
      "instr_count_est": 64.0
    },
    "75836": {
      "addr": 75836.0,
      "name": "sub_1283c",
      "n_blocks": 23.0,
      "total_bytes": 344.0,
      "avg_block_entropy": 3.1325027943167183,
      "std_block_entropy": 0.8217516827658079,
      "bl_count": 6.0,
      "bl_indirect_count": 0.0,
      "svc_count": 0.0,
      "avg_bytes_per_block": 14.95652173848015,
      "instr_count_est": 86.0
    },
    "76164": {
      "addr": 76164.0,
      "name": "sub_12984",
      "n_blocks": 6.0,
      "total_bytes": 104.0,
      "avg_block_entropy": 3.2122275240736635,
      "std_block_entropy": 1.1530005480154266,
      "bl_count": 1.0,
      "bl_indirect_count": 0.0,
      "svc_count": 0.0,
      "avg_bytes_per_block": 17.333333330444443,
      "instr_count_est": 26.0
    },
    "76292": {
      "addr": 76292.0,
      "name": "sub_12a04",
      "n_blocks": 5.0,
      "total_bytes": 116.0,
      "avg_block_entropy": 3.7974344340670307,
      "std_block_entropy": 0.25903474128638165,
      "bl_count": 1.0,
      "bl_indirect_count": 0.0,
      "svc_count": 0.0,
      "avg_bytes_per_block": 23.19999999536,
      "instr_count_est": 29.0
    },
    "76432": {
      "addr": 76432.0,
      "name": "sub_12a90",
      "n_blocks": 5.0,
      "total_bytes": 128.0,
      "avg_block_entropy": 3.855743221808877,
      "std_block_entropy": 0.3412696231837292,
      "bl_count": 1.0,
      "bl_indirect_count": 0.0,
      "svc_count": 0.0,
      "avg_bytes_per_block": 25.59999999488,
      "instr_count_est": 32.0
    },
    "76584": {
      "addr": 76584.0,
      "name": "sub_12b28",
      "n_blocks": 5.0,
      "total_bytes": 100.0,
      "avg_block_entropy": 3.526524689622815,
      "std_block_entropy": 0.47226042425064363,
      "bl_count": 1.0,
      "bl_indirect_count": 0.0,
      "svc_count": 0.0,
      "avg_bytes_per_block": 19.999999996,
      "instr_count_est": 25.0
    },
    "76708": {
      "addr": 76708.0,
      "name": "sub_12ba4",
      "n_blocks": 9.0,
      "total_bytes": 208.0,
      "avg_block_entropy": 3.605935722808073,
      "std_block_entropy": 0.8179710378140174,
      "bl_count": 4.0,
      "bl_indirect_count": 0.0,
      "svc_count": 0.0,
      "avg_bytes_per_block": 23.11111110854321,
      "instr_count_est": 52.0
    },
    "76900": {
      "addr": 76900.0,
      "name": "sub_12c64",
      "n_blocks": 6.0,
      "total_bytes": 160.0,
      "avg_block_entropy": 3.6216576340734807,
      "std_block_entropy": 0.559024420529395,
      "bl_count": 0.0,
      "bl_indirect_count": 0.0,
      "svc_count": 0.0,
      "avg_bytes_per_block": 26.666666662222223,
      "instr_count_est": 40.0
    },
    "77044": {
      "addr": 77044.0,
      "name": "sub_12cf4",
      "n_blocks": 12.0,
      "total_bytes": 220.0,
      "avg_block_entropy": 3.442334910247825,
      "std_block_entropy": 0.8904094803499146,
      "bl_count": 3.0,
      "bl_indirect_count": 0.0,
      "svc_count": 0.0,
      "avg_bytes_per_block": 18.333333331805555,
      "instr_count_est": 55.0
    },
    "77248": {
      "addr": 77248.0,
      "name": "sub_12dc0",
      "n_blocks": 11.0,
      "total_bytes": 248.0,
      "avg_block_entropy": 3.308138496806397,
      "std_block_entropy": 1.0306235897023364,
      "bl_count": 4.0,
      "bl_indirect_count": 0.0,
      "svc_count": 0.0,
      "avg_bytes_per_block": 22.545454543404958,
      "instr_count_est": 62.0
    },
    "77448": {
      "addr": 77448.0,
      "name": "sub_12e88",
      "n_blocks": 30.0,
      "total_bytes": 568.0,
      "avg_block_entropy": 3.3753430854534456,
      "std_block_entropy": 0.7285359105956929,
      "bl_count": 4.0,
      "bl_indirect_count": 0.0,
      "svc_count": 0.0,
      "avg_bytes_per_block": 18.933333332702222,
      "instr_count_est": 142.0
    },
    "77876": {
      "addr": 77876.0,
      "name": "sub_13034",
      "n_blocks": 7.0,
      "total_bytes": 120.0,
      "avg_block_entropy": 3.239590698856033,
      "std_block_entropy": 0.7889605593260962,
      "bl_count": 2.0,
      "bl_indirect_count": 0.0,
      "svc_count": 0.0,
      "avg_bytes_per_block": 17.142857140408164,
      "instr_count_est": 30.0
    },
    "78024": {
      "addr": 78024.0,
      "name": "sub_130c8",
      "n_blocks": 35.0,
      "total_bytes": 472.0,
      "avg_block_entropy": 3.022632065034195,
      "std_block_entropy": 0.837694628751455,
      "bl_count": 13.0,
      "bl_indirect_count": 0.0,
      "svc_count": 0.0,
      "avg_bytes_per_block": 13.485714285328982,
      "instr_count_est": 118.0
    },
    "78444": {
      "addr": 78444.0,
      "name": "sub_1326c",
      "n_blocks": 4.0,
      "total_bytes": 72.0,
      "avg_block_entropy": 3.702459310177535,
      "std_block_entropy": 0.514288568378004,
      "bl_count": 3.0,
      "bl_indirect_count": 0.0,
      "svc_count": 0.0,
      "avg_bytes_per_block": 17.9999999955,
      "instr_count_est": 18.0
    },
    "78520": {
      "addr": 78520.0,
      "name": "sub_132b8",
      "n_blocks": 7.0,
      "total_bytes": 92.0,
      "avg_block_entropy": 3.1432167443659202,
      "std_block_entropy": 0.694844331714985,
      "bl_count": 0.0,
      "bl_indirect_count": 0.0,
      "svc_count": 0.0,
      "avg_bytes_per_block": 13.142857140979592,
      "instr_count_est": 23.0
    },
    "78628": {
      "addr": 78628.0,
      "name": "sub_13324",
      "n_blocks": 1.0,
      "total_bytes": 8.0,
      "avg_block_entropy": 2.5,
      "std_block_entropy": 0.0,
      "bl_count": 0.0,
      "bl_indirect_count": 0.0,
      "svc_count": 0.0,
      "avg_bytes_per_block": 7.999999991999999,
      "instr_count_est": 2.0
    },
    "78636": {
      "addr": 78636.0,
      "name": "sub_1332c",
      "n_blocks": 1.0,
      "total_bytes": 4.0,
      "avg_block_entropy": 2.0,
      "std_block_entropy": 0.0,
      "bl_count": 0.0,
      "bl_indirect_count": 0.0,
      "svc_count": 0.0,
      "avg_bytes_per_block": 3.9999999959999997,
      "instr_count_est": 1.0
    },
    "78640": {
      "addr": 78640.0,
      "name": "sub_13330",
      "n_blocks": 5.0,
      "total_bytes": 52.0,
      "avg_block_entropy": 3.073829244100069,
      "std_block_entropy": 0.6212682910296865,
      "bl_count": 3.0,
      "bl_indirect_count": 0.0,
      "svc_count": 0.0,
      "avg_bytes_per_block": 10.39999999792,
      "instr_count_est": 13.0
    },
    "78696": {
      "addr": 78696.0,
      "name": "sub_13368",
      "n_blocks": 4.0,
      "total_bytes": 76.0,
      "avg_block_entropy": 3.5266526044371,
      "std_block_entropy": 0.41159679460076903,
      "bl_count": 0.0,
      "bl_indirect_count": 0.0,
      "svc_count": 0.0,
      "avg_bytes_per_block": 18.99999999525,
      "instr_count_est": 19.0
    },
    "79376": {
      "addr": 79376.0,
      "name": "sub_13610",
      "n_blocks": 11.0,
      "total_bytes": 268.0,
      "avg_block_entropy": 3.7470327142770246,
      "std_block_entropy": 0.4519341855261211,
      "bl_count": 4.0,
      "bl_indirect_count": 0.0,
      "svc_count": 0.0,
      "avg_bytes_per_block": 24.363636361421488,
      "instr_count_est": 67.0
    },
    "79612": {
      "addr": 79612.0,
      "name": "sub_136fc",
      "n_blocks": 5.0,
      "total_bytes": 52.0,
      "avg_block_entropy": 2.982129994085646,
      "std_block_entropy": 0.5577095005356217,
      "bl_count": 1.0,
      "bl_indirect_count": 0.0,
      "svc_count": 1.0,
      "avg_bytes_per_block": 10.39999999792,
      "instr_count_est": 13.0
    },
    "79656": {
      "addr": 79656.0,
      "name": "sub_13728",
      "n_blocks": 2.0,
      "total_bytes": 20.0,
      "avg_block_entropy": 2.802694271103767,
      "std_block_entropy": 0.05269427110376679,
      "bl_count": 0.0,
      "bl_indirect_count": 0.0,
      "svc_count": 2.0,
      "avg_bytes_per_block": 9.999999995,
      "instr_count_est": 5.0
    },
    "79668": {
      "addr": 79668.0,
      "name": "sub_13734",
      "n_blocks": 3.0,
      "total_bytes": 28.0,
      "avg_block_entropy": 2.8344194449252154,
      "std_block_entropy": 0.6055133553879474,
      "bl_count": 1.0,
      "bl_indirect_count": 0.0,
      "svc_count": 0.0,
      "avg_bytes_per_block": 9.333333330222223,
      "instr_count_est": 7.0
    },
    "79696": {
      "addr": 79696.0,
      "name": "sub_13750",
      "n_blocks": 6.0,
      "total_bytes": 80.0,
      "avg_block_entropy": 3.182501656916181,
      "std_block_entropy": 0.5933979779180856,
      "bl_count": 1.0,
      "bl_indirect_count": 0.0,
      "svc_count": 1.0,
      "avg_bytes_per_block": 13.333333331111112,
      "instr_count_est": 20.0
    },
    "79776": {
      "addr": 79776.0,
      "name": "sub_137a0",
      "n_blocks": 8.0,
      "total_bytes": 168.0,
      "avg_block_entropy": 3.480722568515789,
      "std_block_entropy": 0.9411068509867432,
      "bl_count": 3.0,
      "bl_indirect_count": 0.0,
      "svc_count": 0.0,
      "avg_bytes_per_block": 20.999999997375,
      "instr_count_est": 42.0
    },
    "79924": {
      "addr": 79924.0,
      "name": "sub_13834",
      "n_blocks": 17.0,
      "total_bytes": 400.0,
      "avg_block_entropy": 3.4803057639643593,
      "std_block_entropy": 0.9544304205511024,
      "bl_count": 4.0,
      "bl_indirect_count": 0.0,
      "svc_count": 1.0,
      "avg_bytes_per_block": 23.5294117633218,
      "instr_count_est": 100.0
    },
    "80280": {
      "addr": 80280.0,
      "name": "sub_13998",
      "n_blocks": 5.0,
      "total_bytes": 52.0,
      "avg_block_entropy": 2.982129994085646,
      "std_block_entropy": 0.5577095005356217,
      "bl_count": 1.0,
      "bl_indirect_count": 0.0,
      "svc_count": 1.0,
      "avg_bytes_per_block": 10.39999999792,
      "instr_count_est": 13.0
    },
    "80324": {
      "addr": 80324.0,
      "name": "sub_139c4",
      "n_blocks": 5.0,
      "total_bytes": 52.0,
      "avg_block_entropy": 2.982129994085646,
      "std_block_entropy": 0.5577095005356217,
      "bl_count": 1.0,
      "bl_indirect_count": 0.0,
      "svc_count": 1.0,
      "avg_bytes_per_block": 10.39999999792,
      "instr_count_est": 13.0
    },
    "80368": {
      "addr": 80368.0,
      "name": "sub_139f0",
      "n_blocks": 5.0,
      "total_bytes": 52.0,
      "avg_block_entropy": 2.982129994085646,
      "std_block_entropy": 0.5577095005356217,
      "bl_count": 1.0,
      "bl_indirect_count": 0.0,
      "svc_count": 1.0,
      "avg_bytes_per_block": 10.39999999792,
      "instr_count_est": 13.0
    },
    "80412": {
      "addr": 80412.0,
      "name": "sub_13a1c",
      "n_blocks": 5.0,
      "total_bytes": 52.0,
      "avg_block_entropy": 2.982129994085646,
      "std_block_entropy": 0.5577095005356217,
      "bl_count": 1.0,
      "bl_indirect_count": 0.0,
      "svc_count": 1.0,
      "avg_bytes_per_block": 10.39999999792,
      "instr_count_est": 13.0
    },
    "80456": {
      "addr": 80456.0,
      "name": "sub_13a48",
      "n_blocks": 8.0,
      "total_bytes": 108.0,
      "avg_block_entropy": 2.942317175511045,
      "std_block_entropy": 0.6902658924745708,
      "bl_count": 1.0,
      "bl_indirect_count": 0.0,
      "svc_count": 1.0,
      "avg_bytes_per_block": 13.4999999983125,
      "instr_count_est": 27.0
    },
    "80556": {
      "addr": 80556.0,
      "name": "sub_13aac",
      "n_blocks": 5.0,
      "total_bytes": 52.0,
      "avg_block_entropy": 2.982129994085646,
      "std_block_entropy": 0.5577095005356217,
      "bl_count": 1.0,
      "bl_indirect_count": 0.0,
      "svc_count": 1.0,
      "avg_bytes_per_block": 10.39999999792,
      "instr_count_est": 13.0
    },
    "80600": {
      "addr": 80600.0,
      "name": "sub_13ad8",
      "n_blocks": 8.0,
      "total_bytes": 92.0,
      "avg_block_entropy": 2.645237931727656,
      "std_block_entropy": 0.7932125554014055,
      "bl_count": 2.0,
      "bl_indirect_count": 0.0,
      "svc_count": 0.0,
      "avg_bytes_per_block": 11.4999999985625,
      "instr_count_est": 23.0
    },
    "80688": {
      "addr": 80688.0,
      "name": "sub_13b30",
      "n_blocks": 5.0,
      "total_bytes": 52.0,
      "avg_block_entropy": 2.982129994085646,
      "std_block_entropy": 0.5577095005356217,
      "bl_count": 1.0,
      "bl_indirect_count": 0.0,
      "svc_count": 1.0,
      "avg_bytes_per_block": 10.39999999792,
      "instr_count_est": 13.0
    },
    "80732": {
      "addr": 80732.0,
      "name": "sub_13b5c",
      "n_blocks": 3.0,
      "total_bytes": 784.0,
      "avg_block_entropy": 4.683734784996321,
      "std_block_entropy": 0.29078053755963496,
      "bl_count": 1.0,
      "bl_indirect_count": 0.0,
      "svc_count": 0.0,
      "avg_bytes_per_block": 261.3333332462222,
      "instr_count_est": 196.0
    },
    "81516": {
      "addr": 81516.0,
      "name": "sub_13e6c",
      "n_blocks": 2.0,
      "total_bytes": 204.0,
      "avg_block_entropy": 4.124881873833603,
      "std_block_entropy": 0.14322036173184727,
      "bl_count": 1.0,
      "bl_indirect_count": 0.0,
      "svc_count": 0.0,
      "avg_bytes_per_block": 101.999999949,
      "instr_count_est": 51.0
    },
    "82891": {
      "addr": 82891.0,
      "name": "sub_143cb",
      "n_blocks": 1.0,
      "total_bytes": 2.0,
      "avg_block_entropy": 1.0,
      "std_block_entropy": 0.0,
      "bl_count": 0.0,
      "bl_indirect_count": 0.0,
      "svc_count": 0.0,
      "avg_bytes_per_block": 1.9999999979999998,
      "instr_count_est": 1.0
    },
    "82895": {
      "addr": 82895.0,
      "name": "sub_143cf",
      "n_blocks": 1.0,
      "total_bytes": 2.0,
      "avg_block_entropy": 1.0,
      "std_block_entropy": 0.0,
      "bl_count": 0.0,
      "bl_indirect_count": 0.0,
      "svc_count": 0.0,
      "avg_bytes_per_block": 1.9999999979999998,
      "instr_count_est": 1.0
    },
    "82896": {
      "addr": 82896.0,
      "name": "sub_143d0",
      "n_blocks": 16.0,
      "total_bytes": 272.0,
      "avg_block_entropy": 3.109040268788793,
      "std_block_entropy": 0.9627521802989044,
      "bl_count": 0.0,
      "bl_indirect_count": 0.0,
      "svc_count": 0.0,
      "avg_bytes_per_block": 16.9999999989375,
      "instr_count_est": 68.0
    },
    "83132": {
      "addr": 83132.0,
      "name": "sub_144bc",
      "n_blocks": 2.0,
      "total_bytes": 24.0,
      "avg_block_entropy": 3.4182958340544896,
      "std_block_entropy": 0.0,
      "bl_count": 1.0,
      "bl_indirect_count": 0.0,
      "svc_count": 0.0,
      "avg_bytes_per_block": 11.999999994,
      "instr_count_est": 6.0
    },
    "83156": {
      "addr": 83156.0,
      "name": "sub_144d4",
      "n_blocks": 1.0,
      "total_bytes": 28.0,
      "avg_block_entropy": 3.655045546825804,
      "std_block_entropy": 0.0,
      "bl_count": 0.0,
      "bl_indirect_count": 0.0,
      "svc_count": 0.0,
      "avg_bytes_per_block": 27.999999971999998,
      "instr_count_est": 7.0
    },
    "83192": {
      "addr": 83192.0,
      "name": "sub_144f8",
      "n_blocks": 5.0,
      "total_bytes": 64.0,
      "avg_block_entropy": 3.056450446367605,
      "std_block_entropy": 0.587036699086758,
      "bl_count": 1.0,
      "bl_indirect_count": 0.0,
      "svc_count": 1.0,
      "avg_bytes_per_block": 12.79999999744,
      "instr_count_est": 16.0
    },
    "83252": {
      "addr": 83252.0,
      "name": "sub_14534",
      "n_blocks": 15.0,
      "total_bytes": 380.0,
      "avg_block_entropy": 3.3584009782218396,
      "std_block_entropy": 0.5994195170616938,
      "bl_count": 1.0,
      "bl_indirect_count": 0.0,
      "svc_count": 0.0,
      "avg_bytes_per_block": 25.333333331644443,
      "instr_count_est": 95.0
    },
    "83548": {
      "addr": 83548.0,
      "name": "sub_1465c",
      "n_blocks": 2.0,
      "total_bytes": 24.0,
      "avg_block_entropy": 3.25,
      "std_block_entropy": 0.5,
      "bl_count": 1.0,
      "bl_indirect_count": 0.0,
      "svc_count": 0.0,
      "avg_bytes_per_block": 11.999999994,
      "instr_count_est": 6.0
    },
    "83572": {
      "addr": 83572.0,
      "name": "sub_14674",
      "n_blocks": 4.0,
      "total_bytes": 48.0,
      "avg_block_entropy": 3.042481250360578,
      "std_block_entropy": 0.8637604342227192,
      "bl_count": 0.0,
      "bl_indirect_count": 0.0,
      "svc_count": 0.0,
      "avg_bytes_per_block": 11.999999997,
      "instr_count_est": 12.0
    },
    "83624": {
      "addr": 83624.0,
      "name": "sub_146a8",
      "n_blocks": 1.0,
      "total_bytes": 8.0,
      "avg_block_entropy": 2.75,
      "std_block_entropy": 0.0,
      "bl_count": 0.0,
      "bl_indirect_count": 0.0,
      "svc_count": 0.0,
      "avg_bytes_per_block": 7.999999991999999,
      "instr_count_est": 2.0
    },
    "83632": {
      "addr": 83632.0,
      "name": "sub_146b0",
      "n_blocks": 2.0,
      "total_bytes": 20.0,
      "avg_block_entropy": 3.0,
      "std_block_entropy": 1.0,
      "bl_count": 1.0,
      "bl_indirect_count": 0.0,
      "svc_count": 0.0,
      "avg_bytes_per_block": 9.999999995,
      "instr_count_est": 5.0
    },
    "1048652": {
      "addr": 1048652.0,
      "name": "UnresolvableJumpTarget",
      "n_blocks": 1.0,
      "total_bytes": 4.0,
      "avg_block_entropy": 0.0,
      "std_block_entropy": 0.0,
      "bl_count": 0.0,
      "bl_indirect_count": 0.0,
      "svc_count": 0.0,
      "avg_bytes_per_block": 3.9999999959999997,
      "instr_count_est": 1.0
    },
    "1048656": {
      "addr": 1048656.0,
      "name": "UnresolvableCallTarget",
      "n_blocks": 1.0,
      "total_bytes": 396.0,
      "avg_block_entropy": 0.0,
      "std_block_entropy": 0.0,
      "bl_count": 0.0,
      "bl_indirect_count": 0.0,
      "svc_count": 0.0,
      "avg_bytes_per_block": 395.999999604,
      "instr_count_est": 99.0
    },
    "3145730": {
      "addr": 3145730.0,
      "name": "exit",
      "n_blocks": 1.0,
      "total_bytes": 0.0,
      "avg_block_entropy": 0.0,
      "std_block_entropy": 0.0,
      "bl_count": 0.0,
      "bl_indirect_count": 0.0,
      "svc_count": 0.0,
      "avg_bytes_per_block": 0.0,
      "instr_count_est": 0.0
    },
    "3145732": {
      "addr": 3145732.0,
      "name": "fork",
      "n_blocks": 1.0,
      "total_bytes": 396.0,
      "avg_block_entropy": 0.0,
      "std_block_entropy": 0.0,
      "bl_count": 0.0,
      "bl_indirect_count": 0.0,
      "svc_count": 0.0,
      "avg_bytes_per_block": 395.999999604,
      "instr_count_est": 99.0
    },
    "3145734": {
      "addr": 3145734.0,
      "name": "read",
      "n_blocks": 1.0,
      "total_bytes": 0.0,
      "avg_block_entropy": 0.0,
      "std_block_entropy": 0.0,
      "bl_count": 0.0,
      "bl_indirect_count": 0.0,
      "svc_count": 0.0,
      "avg_bytes_per_block": 0.0,
      "instr_count_est": 0.0
    },
    "3145736": {
      "addr": 3145736.0,
      "name": "write",
      "n_blocks": 1.0,
      "total_bytes": 396.0,
      "avg_block_entropy": 0.0,
      "std_block_entropy": 0.0,
      "bl_count": 0.0,
      "bl_indirect_count": 0.0,
      "svc_count": 0.0,
      "avg_bytes_per_block": 395.999999604,
      "instr_count_est": 99.0
    },
    "3145738": {
      "addr": 3145738.0,
      "name": "open",
      "n_blocks": 1.0,
      "total_bytes": 0.0,
      "avg_block_entropy": 0.0,
      "std_block_entropy": 0.0,
      "bl_count": 0.0,
      "bl_indirect_count": 0.0,
      "svc_count": 0.0,
      "avg_bytes_per_block": 0.0,
      "instr_count_est": 0.0
    },
    "3145740": {
      "addr": 3145740.0,
      "name": "close",
      "n_blocks": 1.0,
      "total_bytes": 396.0,
      "avg_block_entropy": 0.0,
      "std_block_entropy": 0.0,
      "bl_count": 0.0,
      "bl_indirect_count": 0.0,
      "svc_count": 0.0,
      "avg_bytes_per_block": 395.999999604,
      "instr_count_est": 99.0
    },
    "3145754": {
      "addr": 3145754.0,
      "name": "time",
      "n_blocks": 1.0,
      "total_bytes": 0.0,
      "avg_block_entropy": 0.0,
      "std_block_entropy": 0.0,
      "bl_count": 0.0,
      "bl_indirect_count": 0.0,
      "svc_count": 0.0,
      "avg_bytes_per_block": 0.0,
      "instr_count_est": 0.0
    },
    "3145768": {
      "addr": 3145768.0,
      "name": "getpid",
      "n_blocks": 1.0,
      "total_bytes": 396.0,
      "avg_block_entropy": 0.0,
      "std_block_entropy": 0.0,
      "bl_count": 0.0,
      "bl_indirect_count": 0.0,
      "svc_count": 0.0,
      "avg_bytes_per_block": 395.999999604,
      "instr_count_est": 99.0
    },
    "3145802": {
      "addr": 3145802.0,
      "name": "kill",
      "n_blocks": 1.0,
      "total_bytes": 0.0,
      "avg_block_entropy": 0.0,
      "std_block_entropy": 0.0,
      "bl_count": 0.0,
      "bl_indirect_count": 0.0,
      "svc_count": 0.0,
      "avg_bytes_per_block": 0.0,
      "instr_count_est": 0.0
    },
    "3145814": {
      "addr": 3145814.0,
      "name": "times",
      "n_blocks": 1.0,
      "total_bytes": 0.0,
      "avg_block_entropy": 0.0,
      "std_block_entropy": 0.0,
      "bl_count": 0.0,
      "bl_indirect_count": 0.0,
      "svc_count": 0.0,
      "avg_bytes_per_block": 0.0,
      "instr_count_est": 0.0
    },
    "3145818": {
      "addr": 3145818.0,
      "name": "brk",
      "n_blocks": 1.0,
      "total_bytes": 0.0,
      "avg_block_entropy": 0.0,
      "std_block_entropy": 0.0,
      "bl_count": 0.0,
      "bl_indirect_count": 0.0,
      "svc_count": 0.0,
      "avg_bytes_per_block": 0.0,
      "instr_count_est": 0.0
    },
    "3145836": {
      "addr": 3145836.0,
      "name": "ioctl",
      "n_blocks": 1.0,
      "total_bytes": 396.0,
      "avg_block_entropy": 0.0,
      "std_block_entropy": 0.0,
      "bl_count": 0.0,
      "bl_indirect_count": 0.0,
      "svc_count": 0.0,
      "avg_bytes_per_block": 395.999999604,
      "instr_count_est": 99.0
    },
    "3145838": {
      "addr": 3145838.0,
      "name": "fcntl",
      "n_blocks": 1.0,
      "total_bytes": 0.0,
      "avg_block_entropy": 0.0,
      "std_block_entropy": 0.0,
      "bl_count": 0.0,
      "bl_indirect_count": 0.0,
      "svc_count": 0.0,
      "avg_bytes_per_block": 0.0,
      "instr_count_est": 0.0
    },
    "3145856": {
      "addr": 3145856.0,
      "name": "getppid",
      "n_blocks": 1.0,
      "total_bytes": 396.0,
      "avg_block_entropy": 0.0,
      "std_block_entropy": 0.0,
      "bl_count": 0.0,
      "bl_indirect_count": 0.0,
      "svc_count": 0.0,
      "avg_bytes_per_block": 395.999999604,
      "instr_count_est": 99.0
    },
    "3145860": {
      "addr": 3145860.0,
      "name": "setsid",
      "n_blocks": 1.0,
      "total_bytes": 396.0,
      "avg_block_entropy": 0.0,
      "std_block_entropy": 0.0,
      "bl_count": 0.0,
      "bl_indirect_count": 0.0,
      "svc_count": 0.0,
      "avg_bytes_per_block": 395.999999604,
      "instr_count_est": 99.0
    },
    "3145944": {
      "addr": 3145944.0,
      "name": "fstat",
      "n_blocks": 1.0,
      "total_bytes": 396.0,
      "avg_block_entropy": 0.0,
      "std_block_entropy": 0.0,
      "bl_count": 0.0,
      "bl_indirect_count": 0.0,
      "svc_count": 0.0,
      "avg_bytes_per_block": 395.999999604,
      "instr_count_est": 99.0
    },
    "3146008": {
      "addr": 3146008.0,
      "name": "_llseek",
      "n_blocks": 1.0,
      "total_bytes": 396.0,
      "avg_block_entropy": 0.0,
      "std_block_entropy": 0.0,
      "bl_count": 0.0,
      "bl_indirect_count": 0.0,
      "svc_count": 0.0,
      "avg_bytes_per_block": 395.999999604,
      "instr_count_est": 99.0
    },
    "3146012": {
      "addr": 3146012.0,
      "name": "_newselect",
      "n_blocks": 1.0,
      "total_bytes": 396.0,
      "avg_block_entropy": 0.0,
      "std_block_entropy": 0.0,
      "bl_count": 0.0,
      "bl_indirect_count": 0.0,
      "svc_count": 0.0,
      "avg_bytes_per_block": 395.999999604,
      "instr_count_est": 99.0
    },
    "3146052": {
      "addr": 3146052.0,
      "name": "nanosleep",
      "n_blocks": 1.0,
      "total_bytes": 396.0,
      "avg_block_entropy": 0.0,
      "std_block_entropy": 0.0,
      "bl_count": 0.0,
      "bl_indirect_count": 0.0,
      "svc_count": 0.0,
      "avg_bytes_per_block": 395.999999604,
      "instr_count_est": 99.0
    },
    "3146076": {
      "addr": 3146076.0,
      "name": "rt_sigaction",
      "n_blocks": 1.0,
      "total_bytes": 396.0,
      "avg_block_entropy": 0.0,
      "std_block_entropy": 0.0,
      "bl_count": 0.0,
      "bl_indirect_count": 0.0,
      "svc_count": 0.0,
      "avg_bytes_per_block": 395.999999604,
      "instr_count_est": 99.0
    },
    "3146078": {
      "addr": 3146078.0,
      "name": "rt_sigprocmask",
      "n_blocks": 1.0,
      "total_bytes": 0.0,
      "avg_block_entropy": 0.0,
      "std_block_entropy": 0.0,
      "bl_count": 0.0,
      "bl_indirect_count": 0.0,
      "svc_count": 0.0,
      "avg_bytes_per_block": 0.0,
      "instr_count_est": 0.0
    },
    "3146126": {
      "addr": 3146126.0,
      "name": "getuid32",
      "n_blocks": 1.0,
      "total_bytes": 0.0,
      "avg_block_entropy": 0.0,
      "std_block_entropy": 0.0,
      "bl_count": 0.0,
      "bl_indirect_count": 0.0,
      "svc_count": 0.0,
      "avg_bytes_per_block": 0.0,
      "instr_count_est": 0.0
    },
    "3146128": {
      "addr": 3146128.0,
      "name": "getgid32",
      "n_blocks": 1.0,
      "total_bytes": 396.0,
      "avg_block_entropy": 0.0,
      "std_block_entropy": 0.0,
      "bl_count": 0.0,
      "bl_indirect_count": 0.0,
      "svc_count": 0.0,
      "avg_bytes_per_block": 395.999999604,
      "instr_count_est": 99.0
    },
    "3146130": {
      "addr": 3146130.0,
      "name": "geteuid32",
      "n_blocks": 1.0,
      "total_bytes": 0.0,
      "avg_block_entropy": 0.0,
      "std_block_entropy": 0.0,
      "bl_count": 0.0,
      "bl_indirect_count": 0.0,
      "svc_count": 0.0,
      "avg_bytes_per_block": 0.0,
      "instr_count_est": 0.0
    },
    "3146132": {
      "addr": 3146132.0,
      "name": "getegid32",
      "n_blocks": 1.0,
      "total_bytes": 396.0,
      "avg_block_entropy": 0.0,
      "std_block_entropy": 0.0,
      "bl_count": 0.0,
      "bl_indirect_count": 0.0,
      "svc_count": 0.0,
      "avg_bytes_per_block": 395.999999604,
      "instr_count_est": 99.0
    },
    "3146162": {
      "addr": 3146162.0,
      "name": "getdents64",
      "n_blocks": 1.0,
      "total_bytes": 0.0,
      "avg_block_entropy": 0.0,
      "std_block_entropy": 0.0,
      "bl_count": 0.0,
      "bl_indirect_count": 0.0,
      "svc_count": 0.0,
      "avg_bytes_per_block": 0.0,
      "instr_count_est": 0.0
    },
    "3146170": {
      "addr": 3146170.0,
      "name": "fcntl64",
      "n_blocks": 1.0,
      "total_bytes": 0.0,
      "avg_block_entropy": 0.0,
      "std_block_entropy": 0.0,
      "bl_count": 0.0,
      "bl_indirect_count": 0.0,
      "svc_count": 0.0,
      "avg_bytes_per_block": 0.0,
      "instr_count_est": 0.0
    },
    "3146290": {
      "addr": 3146290.0,
      "name": "socket",
      "n_blocks": 1.0,
      "total_bytes": 0.0,
      "avg_block_entropy": 0.0,
      "std_block_entropy": 0.0,
      "bl_count": 0.0,
      "bl_indirect_count": 0.0,
      "svc_count": 0.0,
      "avg_bytes_per_block": 0.0,
      "instr_count_est": 0.0
    },
    "3146292": {
      "addr": 3146292.0,
      "name": "bind",
      "n_blocks": 1.0,
      "total_bytes": 396.0,
      "avg_block_entropy": 0.0,
      "std_block_entropy": 0.0,
      "bl_count": 0.0,
      "bl_indirect_count": 0.0,
      "svc_count": 0.0,
      "avg_bytes_per_block": 395.999999604,
      "instr_count_est": 99.0
    },
    "3146294": {
      "addr": 3146294.0,
      "name": "connect",
      "n_blocks": 1.0,
      "total_bytes": 0.0,
      "avg_block_entropy": 0.0,
      "std_block_entropy": 0.0,
      "bl_count": 0.0,
      "bl_indirect_count": 0.0,
      "svc_count": 0.0,
      "avg_bytes_per_block": 0.0,
      "instr_count_est": 0.0
    },
    "3146296": {
      "addr": 3146296.0,
      "name": "listen",
      "n_blocks": 1.0,
      "total_bytes": 396.0,
      "avg_block_entropy": 0.0,
      "std_block_entropy": 0.0,
      "bl_count": 0.0,
      "bl_indirect_count": 0.0,
      "svc_count": 0.0,
      "avg_bytes_per_block": 395.999999604,
      "instr_count_est": 99.0
    },
    "3146298": {
      "addr": 3146298.0,
      "name": "accept",
      "n_blocks": 1.0,
      "total_bytes": 0.0,
      "avg_block_entropy": 0.0,
      "std_block_entropy": 0.0,
      "bl_count": 0.0,
      "bl_indirect_count": 0.0,
      "svc_count": 0.0,
      "avg_bytes_per_block": 0.0,
      "instr_count_est": 0.0
    },
    "3146300": {
      "addr": 3146300.0,
      "name": "getsockname",
      "n_blocks": 1.0,
      "total_bytes": 396.0,
      "avg_block_entropy": 0.0,
      "std_block_entropy": 0.0,
      "bl_count": 0.0,
      "bl_indirect_count": 0.0,
      "svc_count": 0.0,
      "avg_bytes_per_block": 395.999999604,
      "instr_count_est": 99.0
    },
    "3146306": {
      "addr": 3146306.0,
      "name": "send",
      "n_blocks": 1.0,
      "total_bytes": 0.0,
      "avg_block_entropy": 0.0,
      "std_block_entropy": 0.0,
      "bl_count": 0.0,
      "bl_indirect_count": 0.0,
      "svc_count": 0.0,
      "avg_bytes_per_block": 0.0,
      "instr_count_est": 0.0
    },
    "3146308": {
      "addr": 3146308.0,
      "name": "sendto",
      "n_blocks": 1.0,
      "total_bytes": 396.0,
      "avg_block_entropy": 0.0,
      "std_block_entropy": 0.0,
      "bl_count": 0.0,
      "bl_indirect_count": 0.0,
      "svc_count": 0.0,
      "avg_bytes_per_block": 395.999999604,
      "instr_count_est": 99.0
    },
    "3146310": {
      "addr": 3146310.0,
      "name": "recv",
      "n_blocks": 1.0,
      "total_bytes": 0.0,
      "avg_block_entropy": 0.0,
      "std_block_entropy": 0.0,
      "bl_count": 0.0,
      "bl_indirect_count": 0.0,
      "svc_count": 0.0,
      "avg_bytes_per_block": 0.0,
      "instr_count_est": 0.0
    },
    "3146312": {
      "addr": 3146312.0,
      "name": "recvfrom",
      "n_blocks": 1.0,
      "total_bytes": 396.0,
      "avg_block_entropy": 0.0,
      "std_block_entropy": 0.0,
      "bl_count": 0.0,
      "bl_indirect_count": 0.0,
      "svc_count": 0.0,
      "avg_bytes_per_block": 395.999999604,
      "instr_count_est": 99.0
    },
    "3146316": {
      "addr": 3146316.0,
      "name": "setsockopt",
      "n_blocks": 1.0,
      "total_bytes": 396.0,
      "avg_block_entropy": 0.0,
      "std_block_entropy": 0.0,
      "bl_count": 0.0,
      "bl_indirect_count": 0.0,
      "svc_count": 0.0,
      "avg_bytes_per_block": 395.999999604,
      "instr_count_est": 99.0
    },
    "3146318": {
      "addr": 3146318.0,
      "name": "getsockopt",
      "n_blocks": 1.0,
      "total_bytes": 0.0,
      "avg_block_entropy": 0.0,
      "std_block_entropy": 0.0,
      "bl_count": 0.0,
      "bl_indirect_count": 0.0,
      "svc_count": 0.0,
      "avg_bytes_per_block": 0.0,
      "instr_count_est": 0.0
    }
  }
}