{
  "binary": "dataset/05ff05987a2e5186473de78f9095bd071ac65b901ab9aac4de5acd6cc42f4091.elf",
  "n_nodes": 46,
  "nodes": {
    "60168": {
      "addr": 60168,
      "size": 80,
      "entropy": 4.845191026294643
    },
    "3146112": {
      "addr": 3146112,
      "size": 0,
      "entropy": -0.0
    },
    "60248": {
      "addr": 60248,
      "size": 8,
      "entropy": 3.0
    },
    "62940": {
      "addr": 62940,
      "size": 20,
      "entropy": 3.446439344671016
    },
    "60256": {
      "addr": 60256,
      "size": 16,
      "entropy": 3.5
    },
    "3145736": {
      "addr": 3145736,
      "size": 0,
      "entropy": -0.0
    },
    "60272": {
      "addr": 60272,
      "size": 48,
      "entropy": 4.438721875540868
    },
    "3146488": {
      "addr": 3146488,
      "size": 0,
      "entropy": -0.0
    },
    "60320": {
      "addr": 60320,
      "size": 72,
      "entropy": 4.751105863686464
    },
    "62960": {
      "addr": 62960,
      "size": 12,
      "entropy": 2.584962500721156
    },
    "3145730": {
      "addr": 3145730,
      "size": 0,
      "entropy": 0.0
    },
    "1048656": {
      "addr": 1048656,
      "size": 0,
      "entropy": -0.0
    },
    "60392": {
      "addr": 60392,
      "size": 4,
      "entropy": 2.0
    },
    "32769": {
      "addr": 32769,
      "size": 118,
      "entropy": 2.4261850745282274
    },
    "32945": {
      "addr": 32945,
      "size": 16,
      "entropy": 2.771782221599798
    },
    "32988": {
      "addr": 32988,
      "size": 8,
      "entropy": 3.0
    },
    "32996": {
      "addr": 32996,
      "size": 12,
      "entropy": 3.4182958340544896
    },
    "33008": {
      "addr": 33008,
      "size": 4,
      "entropy": 2.0
    },
    "33033": {
      "addr": 33033,
      "size": 2,
      "entropy": 1.0
    },
    "33035": {
      "addr": 33035,
      "size": 10,
      "entropy": 3.321928094887362
    },
    "33092": {
      "addr": 33092,
      "size": 4,
      "entropy": 2.0
    },
    "1048652": {
      "addr": 1048652,
      "size": 0,
      "entropy": -0.0
    },
    "33016": {
      "addr": 33016,
      "size": 8,
      "entropy": 3.0
    },
    "33028": {
      "addr": 33028,
      "size": 4,
      "entropy": 2.0
    },
    "33146": {
      "addr": 33146,
      "size": 8,
      "entropy": 3.0
    },
    "33208": {
      "addr": 33208,
      "size": 4,
      "entropy": 2.0
    },
    "33213": {
      "addr": 33213,
      "size": 12,
      "entropy": 3.584962500721156
    },
    "33276": {
      "addr": 33276,
      "size": 4,
      "entropy": 2.0
    },
    "33281": {
      "addr": 33281,
      "size": 4,
      "entropy": 2.0
    },
    "49802": {
      "addr": 49802,
      "size": 4,
      "entropy": 2.0
    },
    "49876": {
      "addr": 49876,
      "size": 16,
      "entropy": 3.875
    },
    "50121": {
      "addr": 50121,
      "size": 16,
      "entropy": 4.0
    },
    "49972": {
      "addr": 49972,
      "size": 8,
      "entropy": 3.0
    },
    "50011": {
      "addr": 50011,
      "size": 4,
      "entropy": 2.0
    },
    "50197": {
      "addr": 50197,
      "size": 6,
      "entropy": 2.584962500721156
    },
    "50015": {
      "addr": 50015,
      "size": 8,
      "entropy": 3.0
    },
    "50028": {
      "addr": 50028,
      "size": 4,
      "entropy": 2.0
    },
    "50043": {
      "addr": 50043,
      "size": 22,
      "entropy": 4.368522527728206
    },
    "50081": {
      "addr": 50081,
      "size": 6,
      "entropy": 2.584962500721156
    },
    "50087": {
      "addr": 50087,
      "size": 6,
      "entropy": 2.2516291673878226
    },
    "51467": {
      "addr": 51467,
      "size": 6,
      "entropy": 2.584962500721156
    },
    "50093": {
      "addr": 50093,
      "size": 10,
      "entropy": 3.321928094887362
    },
    "50104": {
      "addr": 50104,
      "size": 4,
      "entropy": 2.0
    },
    "49901": {
      "addr": 49901,
      "size": 8,
      "entropy": 3.0
    },
    "33024": {
      "addr": 33024,
      "size": 4,
      "entropy": 3.0
    },
    "49893": {
      "addr": 49893,
      "size": 8,
      "entropy": 4.0
    }
  }
}